[
    {
        "title": "斗破苍穹350约定比试炼丹（07",
        "url": "https://xiongod.github.io/dpcq2/0350.m4a",
        "duration": "",
        "published": "2024-06-03",
        "createTime": "",
        "chapter": 350,
        "id": "805209be19f041e8bea1ae028307f69a"
    },
    {
        "title": "斗破苍穹351笔试题目龙力丹（07",
        "url": "https://xiongod.github.io/dpcq2/0351.m4a",
        "duration": "",
        "published": "2024-06-03",
        "createTime": "",
        "chapter": 351,
        "id": "a4f9bbe550c14df6adb7648ae4144300"
    },
    {
        "title": "斗破苍穹352幻金火（07",
        "url": "https://xiongod.github.io/dpcq2/0352.m4a",
        "duration": "",
        "published": "2024-06-03",
        "createTime": "",
        "chapter": 352,
        "id": "5bb239023f454b81b0ee7021382c4487"
    },
    {
        "title": "斗破苍穹353半成品（07",
        "url": "https://xiongod.github.io/dpcq2/0353.m4a",
        "duration": "",
        "published": "2024-06-03",
        "createTime": "",
        "chapter": 353,
        "id": "5d384df218ce4d63859c5248c07c7d14"
    },
    {
        "title": "斗破苍穹354波折，成功（07",
        "url": "https://xiongod.github.io/dpcq2/0354.m4a",
        "duration": "",
        "published": "2024-06-03",
        "createTime": "",
        "chapter": 354,
        "id": "bf9f11d509144d10a4428079d4696920"
    },
    {
        "title": "斗破苍穹355招纳炼药师（07",
        "url": "https://xiongod.github.io/dpcq2/0355.m4a",
        "duration": "",
        "published": "2024-06-03",
        "createTime": "",
        "chapter": 355,
        "id": "c0477ead4e3b435289972ab41eef76aa"
    },
    {
        "title": "斗破苍穹356修炼三千雷动（07",
        "url": "https://xiongod.github.io/dpcq2/0356.m4a",
        "duration": "",
        "published": "2024-06-03",
        "createTime": "",
        "chapter": 356,
        "id": "18d1edd0f98d4386870c8b8aaf25dea3"
    },
    {
        "title": "斗破苍穹357炼化风雷之力成功（07",
        "url": "https://xiongod.github.io/dpcq2/0357.m4a",
        "duration": "",
        "published": "2024-06-03",
        "createTime": "",
        "chapter": 357,
        "id": "d158ec6aa61143ff85ef0bc0dcb9800f"
    },
    {
        "title": "斗破苍穹358雷闪（07",
        "url": "https://xiongod.github.io/dpcq2/0358.m4a",
        "duration": "",
        "published": "2024-06-03",
        "createTime": "",
        "chapter": 358,
        "id": "a4cc0525e91b4f6aa7677d29c9a4a8d0"
    },
    {
        "title": "斗破苍穹359地心淬体乳（07",
        "url": "https://xiongod.github.io/dpcq2/0359.m4a",
        "duration": "",
        "published": "2024-06-03",
        "createTime": "",
        "chapter": 359,
        "id": "a354aa76f3aa4da4aba962bb9399dbc4"
    },
    {
        "title": "斗破苍穹360强榜高手，渔翁（07",
        "url": "https://xiongod.github.io/dpcq2/0360.m4a",
        "duration": "",
        "published": "2024-06-03",
        "createTime": "",
        "chapter": 360,
        "id": "0bd9f57217f74e7f87a7b99c8a930c49"
    },
    {
        "title": "斗破苍穹361斗气化翼（07",
        "url": "https://xiongod.github.io/dpcq2/0361.m4a",
        "duration": "",
        "published": "2024-06-03",
        "createTime": "",
        "chapter": 361,
        "id": "873a1f782e534da58c3cf8c380099f1f"
    },
    {
        "title": "斗破苍穹362狂暴血脉（07",
        "url": "https://xiongod.github.io/dpcq2/0362.m4a",
        "duration": "",
        "published": "2024-06-03",
        "createTime": "",
        "chapter": 362,
        "id": "ec23a23ae701429ca2ba5c1d67259ffc"
    },
    {
        "title": "斗破苍穹363蟒猿相斗（07",
        "url": "https://xiongod.github.io/dpcq2/0363.m4a",
        "duration": "",
        "published": "2024-06-03",
        "createTime": "",
        "chapter": 363,
        "id": "874616343e6249c8b87e3aa3c7d9104e"
    },
    {
        "title": "斗破苍穹364寻宝地心淬体乳（07",
        "url": "https://xiongod.github.io/dpcq2/0364.m4a",
        "duration": "",
        "published": "2024-06-03",
        "createTime": "",
        "chapter": 364,
        "id": "500b2dc6fa254311acd0640e9f5bc810"
    },
    {
        "title": "斗破苍穹365真假地心淬体乳（07",
        "url": "https://xiongod.github.io/dpcq2/0365.m4a",
        "duration": "",
        "published": "2024-06-03",
        "createTime": "",
        "chapter": 365,
        "id": "f8e8c186dc604f98bce5eeba332aaa59"
    },
    {
        "title": "斗破苍穹366与美杜莎女王的约定（07",
        "url": "https://xiongod.github.io/dpcq2/0366.m4a",
        "duration": "",
        "published": "2024-06-03",
        "createTime": "",
        "chapter": 366,
        "id": "46f8ecb7489e4d65bd1d982d7b2f5862"
    },
    {
        "title": "斗破苍穹367调配药液（停更通知朋友圈评论和群都有发布，自己不关注的怪我咯）",
        "url": "https://xiongod.github.io/dpcq2/0367.m4a",
        "duration": "",
        "published": "2024-06-03",
        "createTime": "",
        "chapter": 367,
        "id": "9cb1185c168c4b2b8339398484f3e47d"
    },
    {
        "title": "斗破苍穹368九星大斗师（多人剧还不满意更新速度和断更原因，那恢复到一周9更可好）",
        "url": "https://xiongod.github.io/dpcq2/0368.m4a",
        "duration": "",
        "published": "2024-06-03",
        "createTime": "",
        "chapter": 368,
        "id": "2dad4c8c217a43ac807f089379a575c8"
    },
    {
        "title": "斗破苍穹369晋升斗灵（周末愉快，第一更，昨天气话，恢复正常更新）",
        "url": "https://xiongod.github.io/dpcq2/0369.m4a",
        "duration": "",
        "published": "2024-06-03",
        "createTime": "",
        "chapter": 369,
        "id": "5aa57c2e7dbd4a0bbe302c473effcab8"
    },
    {
        "title": "斗破苍穹370回院。冲突，出场（第二更，比心。爱你们）",
        "url": "https://xiongod.github.io/dpcq2/0370.m4a",
        "duration": "",
        "published": "2024-06-03",
        "createTime": "",
        "chapter": 370,
        "id": "1c9e97bd4705412b90bb12a3c83ecb33"
    },
    {
        "title": "斗破苍穹371激战白程（07",
        "url": "https://xiongod.github.io/dpcq2/0371.m4a",
        "duration": "",
        "published": "2024-06-03",
        "createTime": "",
        "chapter": 371,
        "id": "ae2f2573313f46579030949971c06113"
    },
    {
        "title": "斗破苍穹372对战六星斗灵（07",
        "url": "https://xiongod.github.io/dpcq2/0372.m4a",
        "duration": "",
        "published": "2024-06-03",
        "createTime": "",
        "chapter": 372,
        "id": "65a69cafd4fa468b82ca763ebdd5bdf8"
    },
    {
        "title": "斗破苍穹373拼药（07",
        "url": "https://xiongod.github.io/dpcq2/0373.m4a",
        "duration": "",
        "published": "2024-06-03",
        "createTime": "",
        "chapter": 373,
        "id": "b835389ec4f344f1828a43dca19c5e15"
    },
    {
        "title": "斗破苍穹374战斗落幕，霸枪柳擎（07",
        "url": "https://xiongod.github.io/dpcq2/0374.m4a",
        "duration": "",
        "published": "2024-06-03",
        "createTime": "",
        "chapter": 374,
        "id": "e70d4b4ba36e40ac9d2d1c46be36dda4"
    },
    {
        "title": "斗破苍穹375强榜排名（07",
        "url": "https://xiongod.github.io/dpcq2/0375.m4a",
        "duration": "",
        "published": "2024-06-03",
        "createTime": "",
        "chapter": 375,
        "id": "8bafe638ee2e44b881cb44ae994234fa"
    },
    {
        "title": "斗破苍穹376神秘的强榜第一（07",
        "url": "https://xiongod.github.io/dpcq2/0376.m4a",
        "duration": "",
        "published": "2024-06-03",
        "createTime": "",
        "chapter": 376,
        "id": "bd06893a680a495ebe5f81efd4aaf253"
    },
    {
        "title": "斗破苍穹377龙须冰火果（07",
        "url": "https://xiongod.github.io/dpcq2/0377.m4a",
        "duration": "",
        "published": "2024-06-03",
        "createTime": "",
        "chapter": 377,
        "id": "44e274470dc741b28d0f5a7c10b5cc1f"
    },
    {
        "title": "斗破苍穹378神秘白衣小女孩（07",
        "url": "https://xiongod.github.io/dpcq2/0378.m4a",
        "duration": "",
        "published": "2024-06-03",
        "createTime": "",
        "chapter": 378,
        "id": "aff8efb2bdfa4207ac588c54ba0db061"
    },
    {
        "title": "斗破苍穹379最后一种材料（07",
        "url": "https://xiongod.github.io/dpcq2/0379.m4a",
        "duration": "",
        "published": "2024-06-03",
        "createTime": "",
        "chapter": 379,
        "id": "76f2e7434f0f42e283874aee76dad8a9"
    },
    {
        "title": "斗破苍穹380六阶水属性魔核，交换（07",
        "url": "https://xiongod.github.io/dpcq2/0380.m4a",
        "duration": "",
        "published": "2024-06-03",
        "createTime": "",
        "chapter": 380,
        "id": "1f85460253ee4c98a0346b2503ccc746"
    },
    {
        "title": "斗破苍穹381炼制地灵丹（07",
        "url": "https://xiongod.github.io/dpcq2/0381.m4a",
        "duration": "",
        "published": "2024-06-03",
        "createTime": "",
        "chapter": 381,
        "id": "72d7ba265154451fa16fc70347f4224f"
    },
    {
        "title": "斗破苍穹382斗破苍穹382动静（07",
        "url": "https://xiongod.github.io/dpcq2/0382.m4a",
        "duration": "",
        "published": "2024-06-03",
        "createTime": "",
        "chapter": 382,
        "id": "5aa0865d0bcd4410a9c942a8e3298fa2"
    },
    {
        "title": "斗破苍穹383药皇，韩枫！（07",
        "url": "https://xiongod.github.io/dpcq2/0383.m4a",
        "duration": "",
        "published": "2024-06-03",
        "createTime": "",
        "chapter": 383,
        "id": "7ab38fd0c7094df8b1d440c54a65b066"
    },
    {
        "title": "斗破苍穹384丹成，探宝的天赋（07",
        "url": "https://xiongod.github.io/dpcq2/0384.m4a",
        "duration": "",
        "published": "2024-06-03",
        "createTime": "",
        "chapter": 384,
        "id": "281be54ec2764f81a77a9121e9ce0a4e"
    },
    {
        "title": "斗破苍穹385急事（07",
        "url": "https://xiongod.github.io/dpcq2/0385.m4a",
        "duration": "",
        "published": "2024-06-03",
        "createTime": "",
        "chapter": 385,
        "id": "19612e810ce9442284ee0291c12ab7c3"
    },
    {
        "title": "斗破苍穹386族中变故（07",
        "url": "https://xiongod.github.io/dpcq2/0386.m4a",
        "duration": "",
        "published": "2024-06-03",
        "createTime": "",
        "chapter": 386,
        "id": "e93612ce14b0456985e8c20cea419478"
    },
    {
        "title": "斗破苍穹387魂殿参与（08",
        "url": "https://xiongod.github.io/dpcq2/0387.m4a",
        "duration": "",
        "published": "2024-06-03",
        "createTime": "",
        "chapter": 387,
        "id": "94902cb052484709a0d715aff823be71"
    },
    {
        "title": "斗破苍穹388萧厉的打算（08",
        "url": "https://xiongod.github.io/dpcq2/0388.m4a",
        "duration": "",
        "published": "2024-06-03",
        "createTime": "",
        "chapter": 388,
        "id": "8c6f76515a4643ab9e3bf6e828f2f202"
    },
    {
        "title": "斗破苍穹389姚盛（08",
        "url": "https://xiongod.github.io/dpcq2/0389.m4a",
        "duration": "",
        "published": "2024-06-03",
        "createTime": "",
        "chapter": 389,
        "id": "5b9c13bf22b84046a6918f747cae075d"
    },
    {
        "title": "斗破苍穹390初步交锋（08",
        "url": "https://xiongod.github.io/dpcq2/0390.m4a",
        "duration": "",
        "published": "2024-06-03",
        "createTime": "",
        "chapter": 390,
        "id": "5ab07b097ea4437eab37f762e3bd75f0"
    },
    {
        "title": "斗破苍穹391一号修炼室，闭关（08",
        "url": "https://xiongod.github.io/dpcq2/0391.m4a",
        "duration": "",
        "published": "2024-06-03",
        "createTime": "",
        "chapter": 391,
        "id": "ecef2acee8674abe873d9845c3be0e4f"
    },
    {
        "title": "斗破苍穹392陨落心炎提前的暴动（08",
        "url": "https://xiongod.github.io/dpcq2/0392.m4a",
        "duration": "",
        "published": "2024-06-03",
        "createTime": "",
        "chapter": 392,
        "id": "5358734a9f7746ddb9bec3b933137050"
    },
    {
        "title": "斗破苍穹393强榜大赛开始（08",
        "url": "https://xiongod.github.io/dpcq2/0393.m4a",
        "duration": "",
        "published": "2024-06-03",
        "createTime": "",
        "chapter": 393,
        "id": "f7a46f872e824a31992ba822a63b0582"
    },
    {
        "title": "斗破苍穹394冤家路窄（08",
        "url": "https://xiongod.github.io/dpcq2/0394.m4a",
        "duration": "",
        "published": "2024-06-03",
        "createTime": "",
        "chapter": 394,
        "id": "17a15c675908437dbecc9c2cdd0e65f9"
    },
    {
        "title": "斗破苍穹395定对手（08",
        "url": "https://xiongod.github.io/dpcq2/0395.m4a",
        "duration": "",
        "published": "2024-06-03",
        "createTime": "",
        "chapter": 395,
        "id": "f2e8b7ddcd6c4f999f5a6d3e6313e61e"
    },
    {
        "title": "斗破苍穹396紫研和贝崌（08",
        "url": "https://xiongod.github.io/dpcq2/0396.m4a",
        "duration": "",
        "published": "2024-06-03",
        "createTime": "",
        "chapter": 396,
        "id": "3151f6d9ef1941ae9e917cb7012467b2"
    },
    {
        "title": "斗破苍穹397冤家路窄（0810更新，中间缺CV的音没办法后期，客官们勿慌）",
        "url": "https://xiongod.github.io/dpcq2/0397.m4a",
        "duration": "",
        "published": "2024-06-03",
        "createTime": "",
        "chapter": 397,
        "id": "57f54254a6ab450480d945f9ac33e820"
    },
    {
        "title": "斗破苍穹398再站白程（08",
        "url": "https://xiongod.github.io/dpcq2/0398.m4a",
        "duration": "",
        "published": "2024-06-03",
        "createTime": "",
        "chapter": 398,
        "id": "6fd197a3b1f54788bcffa2c749f60ba5"
    },
    {
        "title": "斗破苍穹399青火盔甲（08",
        "url": "https://xiongod.github.io/dpcq2/0399.m4a",
        "duration": "",
        "published": "2024-06-03",
        "createTime": "",
        "chapter": 399,
        "id": "f328aa4b21af4e4fbbfa72e62abf82b8"
    },
    {
        "title": "斗破苍穹400柳擎的出场（08",
        "url": "https://xiongod.github.io/dpcq2/0400.m4a",
        "duration": "",
        "published": "2024-06-03",
        "createTime": "",
        "chapter": 400,
        "id": "9c3c9e101ad5403f9102cd1a30007693"
    },
    {
        "title": "斗破苍穹401大裂劈棺爪（08",
        "url": "https://xiongod.github.io/dpcq2/0401.m4a",
        "duration": "",
        "published": "2024-06-03",
        "createTime": "",
        "chapter": 401,
        "id": "3f8a011f3aec4438ad6460e2477f8521"
    },
    {
        "title": "斗破苍穹402对战姚盛（08",
        "url": "https://xiongod.github.io/dpcq2/0402.m4a",
        "duration": "",
        "published": "2024-06-03",
        "createTime": "",
        "chapter": 402,
        "id": "a4c7909a7d1448078728478de201bd43"
    },
    {
        "title": "斗破苍穹403黑水界（08",
        "url": "https://xiongod.github.io/dpcq2/0403.m4a",
        "duration": "",
        "published": "2024-06-03",
        "createTime": "",
        "chapter": 403,
        "id": "4f593e8a57474c99ab147e8646b3a9f2"
    },
    {
        "title": "斗破苍穹404破解黑水界（08",
        "url": "https://xiongod.github.io/dpcq2/0404.m4a",
        "duration": "",
        "published": "2024-06-03",
        "createTime": "",
        "chapter": 404,
        "id": "ab3b704cd01f47caae245cf87cac948f"
    },
    {
        "title": "斗破苍穹405胜！（08",
        "url": "https://xiongod.github.io/dpcq2/0405.m4a",
        "duration": "",
        "published": "2024-06-03",
        "createTime": "",
        "chapter": 405,
        "id": "fd3b2832b83e42b0a94c03544185b3e6"
    },
    {
        "title": "斗破苍穹406一缠一罡（08",
        "url": "https://xiongod.github.io/dpcq2/0406.m4a",
        "duration": "",
        "published": "2024-06-03",
        "createTime": "",
        "chapter": 406,
        "id": "929dc19a19714cd7a9bc4015005c5815"
    },
    {
        "title": "斗破苍穹407卷轴（08",
        "url": "https://xiongod.github.io/dpcq2/0407.m4a",
        "duration": "",
        "published": "2024-06-03",
        "createTime": "",
        "chapter": 407,
        "id": "637b7a30cd504a01b4c149ee0357be56"
    },
    {
        "title": "斗破苍穹408新人黑马与老牌强者的交锋！（08",
        "url": "https://xiongod.github.io/dpcq2/0408.m4a",
        "duration": "",
        "published": "2024-06-03",
        "createTime": "",
        "chapter": 408,
        "id": "a6449a89bfbb41b1bf8bb7f1f3c889f9"
    },
    {
        "title": "斗破苍穹409沸腾（08",
        "url": "https://xiongod.github.io/dpcq2/0409.m4a",
        "duration": "",
        "published": "2024-06-03",
        "createTime": "",
        "chapter": 409,
        "id": "6eee1ef43a964501a29a7b39072fc2ac"
    },
    {
        "title": "斗破苍穹410八极崩与大裂劈棺爪的碰撞！（08",
        "url": "https://xiongod.github.io/dpcq2/0410.m4a",
        "duration": "",
        "published": "2024-06-03",
        "createTime": "",
        "chapter": 410,
        "id": "076712f4e3bb4d67987578d6a6c79522"
    },
    {
        "title": "斗破苍穹411火莲斗技，爆！（08",
        "url": "https://xiongod.github.io/dpcq2/0411.m4a",
        "duration": "",
        "published": "2024-06-03",
        "createTime": "",
        "chapter": 411,
        "id": "112805028a014568822d12e94f1c2e72"
    },
    {
        "title": "斗破苍穹412一招定胜负（07",
        "url": "https://xiongod.github.io/dpcq2/0412.m4a",
        "duration": "",
        "published": "2024-06-03",
        "createTime": "",
        "chapter": 412,
        "id": "01cbb17a17774869804b814da38158eb"
    },
    {
        "title": "斗破苍穹413两败俱伤（08",
        "url": "https://xiongod.github.io/dpcq2/0413.m4a",
        "duration": "",
        "published": "2024-06-03",
        "createTime": "",
        "chapter": 413,
        "id": "def902d005bd46e8b96d454f0464b924"
    },
    {
        "title": "斗破苍穹414还有口气！并列第十！（08",
        "url": "https://xiongod.github.io/dpcq2/0414.m4a",
        "duration": "",
        "published": "2024-06-03",
        "createTime": "",
        "chapter": 414,
        "id": "1abd25693886420db3cb0a511243fb24"
    },
    {
        "title": "斗破苍穹415实力晋升（08",
        "url": "https://xiongod.github.io/dpcq2/0415.m4a",
        "duration": "",
        "published": "2024-06-03",
        "createTime": "",
        "chapter": 415,
        "id": "45972ba38f154f28b5edb14bd9f53291"
    },
    {
        "title": "斗破苍穹416黑湮军副统领，翎泉（08",
        "url": "https://xiongod.github.io/dpcq2/0416.m4a",
        "duration": "",
        "published": "2024-06-03",
        "createTime": "",
        "chapter": 416,
        "id": "d18ff4aaac3c4f7584e62ccf5c1bf220"
    },
    {
        "title": "斗破苍穹417分离（08",
        "url": "https://xiongod.github.io/dpcq2/0417.m4a",
        "duration": "",
        "published": "2024-06-03",
        "createTime": "",
        "chapter": 417,
        "id": "59c987b94370475c893569b2a6dd0338"
    },
    {
        "title": "斗破苍穹418进入天焚炼气塔底层（08",
        "url": "https://xiongod.github.io/dpcq2/0418.m4a",
        "duration": "",
        "published": "2024-06-03",
        "createTime": "",
        "chapter": 418,
        "id": "d74d5a8686fc4856a51d47cc32ac7f7f"
    },
    {
        "title": "斗破苍穹419锻体之痛（08",
        "url": "https://xiongod.github.io/dpcq2/0419.m4a",
        "duration": "",
        "published": "2024-06-03",
        "createTime": "",
        "chapter": 419,
        "id": "38f153544492476db0158677ecce1638"
    },
    {
        "title": "斗破苍穹420陨落心炎，爆发！（08",
        "url": "https://xiongod.github.io/dpcq2/0420.m4a",
        "duration": "",
        "published": "2024-06-03",
        "createTime": "",
        "chapter": 420,
        "id": "1f1b908de1844948ba58b22162021f05"
    },
    {
        "title": "斗破苍穹421陨落心炎，破塔（08",
        "url": "https://xiongod.github.io/dpcq2/0421.m4a",
        "duration": "",
        "published": "2024-06-03",
        "createTime": "",
        "chapter": 421,
        "id": "c7372364885e4fa0810286b5c27f3ab2"
    },
    {
        "title": "斗破苍穹422千层封阵失败（08",
        "url": "https://xiongod.github.io/dpcq2/0422.m4a",
        "duration": "",
        "published": "2024-06-03",
        "createTime": "",
        "chapter": 422,
        "id": "cf4c77a7a4914685ab3c04661a7aa164"
    },
    {
        "title": "斗破苍穹423黑角域，呼朋唤友（08",
        "url": "https://xiongod.github.io/dpcq2/0423.m4a",
        "duration": "",
        "published": "2024-06-03",
        "createTime": "",
        "chapter": 423,
        "id": "2233a71bd2924cd28ff349e97b851750"
    },
    {
        "title": "斗破苍穹424残卷焚决（08",
        "url": "https://xiongod.github.io/dpcq2/0424.m4a",
        "duration": "",
        "published": "2024-06-03",
        "createTime": "",
        "chapter": 424,
        "id": "f25df820813c4ad295810a7327febcdd"
    },
    {
        "title": "斗破苍穹425混乱大战（08",
        "url": "https://xiongod.github.io/dpcq2/0425.m4a",
        "duration": "",
        "published": "2024-06-03",
        "createTime": "",
        "chapter": 425,
        "id": "2fcbcb3037294521a4bf5ca118590408"
    },
    {
        "title": "斗破苍穹426对战范崂（08",
        "url": "https://xiongod.github.io/dpcq2/0426.m4a",
        "duration": "",
        "published": "2024-06-03",
        "createTime": "",
        "chapter": 426,
        "id": "804e8e2707854d8cbbf6ace6aa5bf1ae"
    },
    {
        "title": "斗破苍穹427三人援手（08",
        "url": "https://xiongod.github.io/dpcq2/0427.m4a",
        "duration": "",
        "published": "2024-06-03",
        "createTime": "",
        "chapter": 427,
        "id": "98d47ecc0b6845f88cc3d1b55521e4d8"
    },
    {
        "title": "斗破苍穹428海心焰（08",
        "url": "https://xiongod.github.io/dpcq2/0428.m4a",
        "duration": "",
        "published": "2024-06-03",
        "createTime": "",
        "chapter": 428,
        "id": "ba17a8ed02164df4a137da30340d9120"
    },
    {
        "title": "斗破苍穹429惊天大爆炸（08",
        "url": "https://xiongod.github.io/dpcq2/0429.m4a",
        "duration": "",
        "published": "2024-06-03",
        "createTime": "",
        "chapter": 429,
        "id": "0271d7f93e5d46dc887a3d7b41b2858b"
    },
    {
        "title": "斗破苍穹430范崂落败（08",
        "url": "https://xiongod.github.io/dpcq2/0430.m4a",
        "duration": "",
        "published": "2024-06-03",
        "createTime": "",
        "chapter": 430,
        "id": "f0851e593b8546a7bffbff67c6f0869b"
    },
    {
        "title": "斗破苍穹431封印无效(08",
        "url": "https://xiongod.github.io/dpcq2/0431.m4a",
        "duration": "",
        "published": "2024-06-03",
        "createTime": "",
        "chapter": 431,
        "id": "91498a212e4d42b2af74823ca2816544"
    },
    {
        "title": "斗破苍穹432陨落心炎，破塔。（08",
        "url": "https://xiongod.github.io/dpcq2/0432.m4a",
        "duration": "",
        "published": "2024-06-03",
        "createTime": "",
        "chapter": 432,
        "id": "cb925b337a4740838529827a5dacb283"
    },
    {
        "title": "斗破苍穹433被盯上了（08",
        "url": "https://xiongod.github.io/dpcq2/0433.m4a",
        "duration": "",
        "published": "2024-06-03",
        "createTime": "",
        "chapter": 433,
        "id": "1d94b46c814c451192ffb3d6ab9816c8"
    },
    {
        "title": "斗破苍穹434陨落心炎本体（08",
        "url": "https://xiongod.github.io/dpcq2/0434.m4a",
        "duration": "",
        "published": "2024-06-03",
        "createTime": "",
        "chapter": 434,
        "id": "815d9fed7ee748a4b913d5fc602ebe4e"
    },
    {
        "title": "斗破苍穹435交锋与恐惧（08",
        "url": "https://xiongod.github.io/dpcq2/0435.m4a",
        "duration": "",
        "published": "2024-06-03",
        "createTime": "",
        "chapter": 435,
        "id": "6dfae42214cf4e70b4b92b5bf38961ab"
    },
    {
        "title": "斗破苍穹436大型佛怒火莲（08",
        "url": "https://xiongod.github.io/dpcq2/0436.m4a",
        "duration": "",
        "published": "2024-06-03",
        "createTime": "",
        "chapter": 436,
        "id": "4578176d305b49fd9bf706890a628736"
    },
    {
        "title": "斗破苍穹437吞噬，封印（08",
        "url": "https://xiongod.github.io/dpcq2/0437.m4a",
        "duration": "",
        "published": "2024-06-03",
        "createTime": "",
        "chapter": 437,
        "id": "6acfd517fb1f4060bb44b6b4bfab6fe6"
    },
    {
        "title": "斗破苍穹438绝境，岩浆世界（08",
        "url": "https://xiongod.github.io/dpcq2/0438.m4a",
        "duration": "",
        "published": "2024-06-03",
        "createTime": "",
        "chapter": 438,
        "id": "f4b219394c9448649b154e99cb502e6b"
    },
    {
        "title": "斗破苍穹439绝境，美杜莎女王现（08",
        "url": "https://xiongod.github.io/dpcq2/0439.m4a",
        "duration": "",
        "published": "2024-06-03",
        "createTime": "",
        "chapter": 439,
        "id": "7099d34e0b7a40419e731c51d6c843b7"
    },
    {
        "title": "斗破苍穹440生死之段（08",
        "url": "https://xiongod.github.io/dpcq2/0440.m4a",
        "duration": "",
        "published": "2024-06-03",
        "createTime": "",
        "chapter": 440,
        "id": "889285b9bc604cc4858530e0dcba0de5"
    },
    {
        "title": "斗破苍穹441缓慢的蜕变（09",
        "url": "https://xiongod.github.io/dpcq2/0441.m4a",
        "duration": "",
        "published": "2024-06-03",
        "createTime": "",
        "chapter": 441,
        "id": "1ff1c0e9946a475a9bcaf23e75698786"
    },
    {
        "title": "斗破苍穹442局面反转，抓捕陨落心炎！（09",
        "url": "https://xiongod.github.io/dpcq2/0442.m4a",
        "duration": "",
        "published": "2024-06-03",
        "createTime": "",
        "chapter": 442,
        "id": "ee393bf0d1454437856594f2fe25ce6f"
    },
    {
        "title": "斗破苍穹443侵蚀，炼化，融合！（09",
        "url": "https://xiongod.github.io/dpcq2/0443.m4a",
        "duration": "",
        "published": "2024-06-03",
        "createTime": "",
        "chapter": 443,
        "id": "3ffe5dc010ca4dc7b5d924a11da90f21"
    },
    {
        "title": "斗破苍穹444融合成功！云岚宗的诡异（09",
        "url": "https://xiongod.github.io/dpcq2/0444.m4a",
        "duration": "",
        "published": "2024-06-03",
        "createTime": "",
        "chapter": 444,
        "id": "41711a7d0224416a955eb6e8ceaf4939"
    },
    {
        "title": "斗破苍穹445异火相融后遗症（09",
        "url": "https://xiongod.github.io/dpcq2/0445.m4a",
        "duration": "",
        "published": "2024-06-03",
        "createTime": "",
        "chapter": 445,
        "id": "72d2d1b892364f658407d193909f9e50"
    },
    {
        "title": "斗破苍穹446破塔（09",
        "url": "https://xiongod.github.io/dpcq2/0446.m4a",
        "duration": "",
        "published": "2024-06-03",
        "createTime": "",
        "chapter": 446,
        "id": "cea2d3d2f0424cc582c7f60f8498776a"
    },
    {
        "title": "斗破苍穹447一招。（09",
        "url": "https://xiongod.github.io/dpcq2/0447.m4a",
        "duration": "",
        "published": "2024-06-03",
        "createTime": "",
        "chapter": 447,
        "id": "086c20e01c6c4b2a912dadd4693fba29"
    },
    {
        "title": "斗破苍穹448人造陨落心炎（09",
        "url": "https://xiongod.github.io/dpcq2/0448.m4a",
        "duration": "",
        "published": "2024-06-03",
        "createTime": "",
        "chapter": 448,
        "id": "7132d0d107574a038a996bc5de3c114e"
    },
    {
        "title": "斗破苍穹449召集人手。（09",
        "url": "https://xiongod.github.io/dpcq2/0449.m4a",
        "duration": "",
        "published": "2024-06-03",
        "createTime": "",
        "chapter": 449,
        "id": "eca45d93ae0f42bf89d001584cbd2eea"
    },
    {
        "title": "斗破苍穹450（09",
        "url": "https://xiongod.github.io/dpcq2/0450.m4a",
        "duration": "",
        "published": "2024-06-03",
        "createTime": "",
        "chapter": 450,
        "id": "57b09eb4c7424dcc8a2e67dbe51b1b0e"
    },
    {
        "title": "斗破苍穹451喝退美杜莎（09",
        "url": "https://xiongod.github.io/dpcq2/0451.m4a",
        "duration": "",
        "published": "2024-06-03",
        "createTime": "",
        "chapter": 451,
        "id": "adb5540b7b374ee5bd381a7f9a86b6f9"
    },
    {
        "title": "斗破苍穹452援兵（09",
        "url": "https://xiongod.github.io/dpcq2/0452.m4a",
        "duration": "",
        "published": "2024-06-03",
        "createTime": "",
        "chapter": 452,
        "id": "5772be9c241b42a99d1858fb4d86b12b"
    },
    {
        "title": "斗破苍穹453大开杀戒（09",
        "url": "https://xiongod.github.io/dpcq2/0453.m4a",
        "duration": "",
        "published": "2024-06-03",
        "createTime": "",
        "chapter": 453,
        "id": "7f527c063c314de5895c7eb619d52817"
    },
    {
        "title": "斗破苍穹454噬生丹（09",
        "url": "https://xiongod.github.io/dpcq2/0454.m4a",
        "duration": "",
        "published": "2024-06-03",
        "createTime": "",
        "chapter": 454,
        "id": "d54c4e0b504046c78b24b87e8a816e86"
    },
    {
        "title": "斗破苍穹455大战来临（09",
        "url": "https://xiongod.github.io/dpcq2/0455.m4a",
        "duration": "",
        "published": "2024-06-03",
        "createTime": "",
        "chapter": 455,
        "id": "e9dba13361d94162afdb0b03d04d2853"
    },
    {
        "title": "斗破苍穹456洗刷内院的耻辱就看今天（09",
        "url": "https://xiongod.github.io/dpcq2/0456.m4a",
        "duration": "",
        "published": "2024-06-03",
        "createTime": "",
        "chapter": 456,
        "id": "48aa84f127aa483da2f0ce7756adac3f"
    },
    {
        "title": "斗破苍穹457初步交锋（重合部分已替换，原谅我吧，米娜桑）",
        "url": "https://xiongod.github.io/dpcq2/0457.m4a",
        "duration": "",
        "published": "2024-06-03",
        "createTime": "",
        "chapter": 457,
        "id": "a6b72ac8709e494196c6e1d9b6e1fd58"
    },
    {
        "title": "斗破苍穹458同门之战",
        "url": "https://xiongod.github.io/dpcq2/0458.m4a",
        "duration": "",
        "published": "2024-06-03",
        "createTime": "",
        "chapter": 458,
        "id": "44fc3f708aad4b53a680af2624208eca"
    },
    {
        "title": "斗破苍穹459半只脚踏入斗宗的韩枫（09",
        "url": "https://xiongod.github.io/dpcq2/0459.m4a",
        "duration": "",
        "published": "2024-06-03",
        "createTime": "",
        "chapter": 459,
        "id": "eec8c4ade853428993e7951c60b8b144"
    },
    {
        "title": "斗破苍穹460翡翠火莲（09",
        "url": "https://xiongod.github.io/dpcq2/0460.m4a",
        "duration": "",
        "published": "2024-06-03",
        "createTime": "",
        "chapter": 460,
        "id": "4eef300961e841078a75d100cf532da1"
    },
    {
        "title": "斗破苍穹461魂殿再现（09",
        "url": "https://xiongod.github.io/dpcq2/0461.m4a",
        "duration": "",
        "published": "2024-06-03",
        "createTime": "",
        "chapter": 461,
        "id": "bd299fd9d5c8418f9d06fce368a58e22"
    },
    {
        "title": "斗破苍穹462幽海纳戒（09",
        "url": "https://xiongod.github.io/dpcq2/0462.m4a",
        "duration": "",
        "published": "2024-06-03",
        "createTime": "",
        "chapter": 462,
        "id": "82a79c03e4274da18bce2994bacfcf1a"
    },
    {
        "title": "斗破苍穹463闭关疗伤（09",
        "url": "https://xiongod.github.io/dpcq2/0463.m4a",
        "duration": "",
        "published": "2024-06-03",
        "createTime": "",
        "chapter": 463,
        "id": "979c84d86e4c4ad7958166f3ac45e7c5"
    },
    {
        "title": "斗破苍穹464帝印决，打算（09",
        "url": "https://xiongod.github.io/dpcq2/0464.m4a",
        "duration": "",
        "published": "2024-06-03",
        "createTime": "",
        "chapter": 464,
        "id": "7fcb6b4a110c425f96830f6a736ab5e0"
    },
    {
        "title": "斗破苍穹465建立势力，与美杜莎的交易（09",
        "url": "https://xiongod.github.io/dpcq2/0465.m4a",
        "duration": "",
        "published": "2024-06-03",
        "createTime": "",
        "chapter": 465,
        "id": "aadaf6f49fc645a597cf64b13a7f2b45"
    },
    {
        "title": "斗破苍穹466修炼开山印（09",
        "url": "https://xiongod.github.io/dpcq2/0466.m4a",
        "duration": "",
        "published": "2024-06-03",
        "createTime": "",
        "chapter": 466,
        "id": "3443957c8ac44340932abb35e2caec3e"
    },
    {
        "title": "斗破苍穹467三大势力（09",
        "url": "https://xiongod.github.io/dpcq2/0467.m4a",
        "duration": "",
        "published": "2024-06-03",
        "createTime": "",
        "chapter": 467,
        "id": "bd8a437558974084bc1f8c306cb5bc21"
    },
    {
        "title": "斗破苍穹468拉取帮手（09",
        "url": "https://xiongod.github.io/dpcq2/0468.m4a",
        "duration": "",
        "published": "2024-06-03",
        "createTime": "",
        "chapter": 468,
        "id": "aafaf7c5c6684050ab279454ce1bf1bb"
    },
    {
        "title": "斗破苍穹469收罗药材（09",
        "url": "https://xiongod.github.io/dpcq2/0469.m4a",
        "duration": "",
        "published": "2024-06-03",
        "createTime": "",
        "chapter": 469,
        "id": "ef0bbe521d2641c9b235bf9af363eb11"
    },
    {
        "title": "斗破苍穹470炼制复灵紫丹（09",
        "url": "https://xiongod.github.io/dpcq2/0470.m4a",
        "duration": "",
        "published": "2024-06-03",
        "createTime": "",
        "chapter": 470,
        "id": "418bcf8fa44342b18b7020f855999824"
    },
    {
        "title": "斗破苍穹471丹药拍卖会，震慑（09",
        "url": "https://xiongod.github.io/dpcq2/0471.m4a",
        "duration": "",
        "published": "2024-06-03",
        "createTime": "",
        "chapter": 471,
        "id": "f32e92b394da47ba8d4f9c48c6a175eb"
    },
    {
        "title": "斗破苍穹472拍卖结束（09",
        "url": "https://xiongod.github.io/dpcq2/0472.m4a",
        "duration": "",
        "published": "2024-06-03",
        "createTime": "",
        "chapter": 472,
        "id": "e7ff22a3472546e68ffac270de161f3a"
    },
    {
        "title": "斗破苍穹473修复药液（09",
        "url": "https://xiongod.github.io/dpcq2/0473.m4a",
        "duration": "",
        "published": "2024-06-03",
        "createTime": "",
        "chapter": 473,
        "id": "00c1468071c344b0ba03cffde3bf5017"
    },
    {
        "title": "斗破苍穹474药老苏醒（09",
        "url": "https://xiongod.github.io/dpcq2/0474.m4a",
        "duration": "",
        "published": "2024-06-03",
        "createTime": "",
        "chapter": 474,
        "id": "46e3b3739a44416fa93c09a546f01b16"
    },
    {
        "title": "斗破苍穹475炼制躯体的材料（09",
        "url": "https://xiongod.github.io/dpcq2/0475.m4a",
        "duration": "",
        "published": "2024-06-03",
        "createTime": "",
        "chapter": 475,
        "id": "fb19d1932b0947a79c52c6e7f37ec4d1"
    },
    {
        "title": "斗破苍穹476寻解之法，恢复（09",
        "url": "https://xiongod.github.io/dpcq2/0476.m4a",
        "duration": "",
        "published": "2024-06-03",
        "createTime": "",
        "chapter": 476,
        "id": "aa5751fc877c4d2f985da1907957b769"
    },
    {
        "title": "斗破苍穹477姚氏三兄弟（09",
        "url": "https://xiongod.github.io/dpcq2/0477.m4a",
        "duration": "",
        "published": "2024-06-03",
        "createTime": "",
        "chapter": 477,
        "id": "0409c18e4eaa4c8d96768a2983048824"
    },
    {
        "title": "斗破苍穹478照看安置磐门（09",
        "url": "https://xiongod.github.io/dpcq2/0478.m4a",
        "duration": "",
        "published": "2024-06-03",
        "createTime": "",
        "chapter": 478,
        "id": "46cdf97bf1414d7bb98c43e5554b70e6"
    },
    {
        "title": "斗破苍穹479十招（09",
        "url": "https://xiongod.github.io/dpcq2/0479.m4a",
        "duration": "",
        "published": "2024-06-03",
        "createTime": "",
        "chapter": 479,
        "id": "1ae488c99f694946bfb1e91997fd408f"
    },
    {
        "title": "斗破苍穹480短暂的安宁（09",
        "url": "https://xiongod.github.io/dpcq2/0480.m4a",
        "duration": "",
        "published": "2024-06-03",
        "createTime": "",
        "chapter": 480,
        "id": "1ae52813f15c4ac3bffdd6ab698f80af"
    },
    {
        "title": "斗破苍穹481离开内院（09",
        "url": "https://xiongod.github.io/dpcq2/0481.m4a",
        "duration": "",
        "published": "2024-06-03",
        "createTime": "",
        "chapter": 481,
        "id": "e9dc50224fd14b9cad372d9fa44f65fa"
    },
    {
        "title": "斗破苍穹482启程回归加玛！（09",
        "url": "https://xiongod.github.io/dpcq2/0482.m4a",
        "duration": "",
        "published": "2024-06-03",
        "createTime": "",
        "chapter": 482,
        "id": "bb70fadbaa1646658f2a7a9d8db3a509"
    },
    {
        "title": "斗破苍穹483万里之遥，归心切（09",
        "url": "https://xiongod.github.io/dpcq2/0483.m4a",
        "duration": "",
        "published": "2024-06-03",
        "createTime": "",
        "chapter": 483,
        "id": "11b05c591be94376a98fdac401d36e2c"
    },
    {
        "title": "斗破苍穹484镇鬼关！故人！（09",
        "url": "https://xiongod.github.io/dpcq2/0484.m4a",
        "duration": "",
        "published": "2024-06-03",
        "createTime": "",
        "chapter": 484,
        "id": "5c29f025259145cfabc7b4dd77ec9980"
    },
    {
        "title": "斗破苍穹485木铁云帆蒙力（09",
        "url": "https://xiongod.github.io/dpcq2/0485.m4a",
        "duration": "",
        "published": "2024-06-03",
        "createTime": "",
        "chapter": 485,
        "id": "bcd493e9b501479c85a02d1af162bc66"
    },
    {
        "title": "斗破苍穹486加玛情势（09",
        "url": "https://xiongod.github.io/dpcq2/0486.m4a",
        "duration": "",
        "published": "2024-06-03",
        "createTime": "",
        "chapter": 486,
        "id": "9f8911a763a74f6d919af7d94e919e21"
    },
    {
        "title": "斗破苍穹487云山筹谋（09",
        "url": "https://xiongod.github.io/dpcq2/0487.m4a",
        "duration": "",
        "published": "2024-06-03",
        "createTime": "",
        "chapter": 487,
        "id": "7adabc037a2049e3b247fb3188b17bd5"
    },
    {
        "title": "斗破苍穹488米特尔之难（09",
        "url": "https://xiongod.github.io/dpcq2/0488.m4a",
        "duration": "",
        "published": "2024-06-03",
        "createTime": "",
        "chapter": 488,
        "id": "b5302a037dca44a38e26070d9cf7cd16"
    },
    {
        "title": "斗破苍穹489血战米特尔家族（09",
        "url": "https://xiongod.github.io/dpcq2/0489.m4a",
        "duration": "",
        "published": "2024-06-03",
        "createTime": "",
        "chapter": 489,
        "id": "241ec80375a846d8acd20c0203bb7fec"
    },
    {
        "title": "斗破苍穹490赶至帝都！（09",
        "url": "https://xiongod.github.io/dpcq2/0490.m4a",
        "duration": "",
        "published": "2024-06-03",
        "createTime": "",
        "chapter": 490,
        "id": "1dfb48711c9b4244b0c2bca395fb706b"
    },
    {
        "title": "斗破苍穹491讨债！（09",
        "url": "https://xiongod.github.io/dpcq2/0491.m4a",
        "duration": "",
        "published": "2024-06-03",
        "createTime": "",
        "chapter": 491,
        "id": "dc667e504de2448cbd0ea131518d0daa"
    },
    {
        "title": "斗破苍穹492大开杀戒（09",
        "url": "https://xiongod.github.io/dpcq2/0492.m4a",
        "duration": "",
        "published": "2024-06-03",
        "createTime": "",
        "chapter": 492,
        "id": "0513bcdecce5439cbdfdbf0cc829a1eb"
    },
    {
        "title": "斗破苍穹493横扫（09",
        "url": "https://xiongod.github.io/dpcq2/0493.m4a",
        "duration": "",
        "published": "2024-06-03",
        "createTime": "",
        "chapter": 493,
        "id": "8d6a40326e804362b76d77bc7f837060"
    },
    {
        "title": "斗破苍穹494云岚宗的震惊（09",
        "url": "https://xiongod.github.io/dpcq2/0494.m4a",
        "duration": "",
        "published": "2024-06-03",
        "createTime": "",
        "chapter": 494,
        "id": "9b40491495e8430396722c9fbf650720"
    },
    {
        "title": "斗破苍穹495势（09",
        "url": "https://xiongod.github.io/dpcq2/0495.m4a",
        "duration": "",
        "published": "2024-06-03",
        "createTime": "",
        "chapter": 495,
        "id": "d7f263382407423aa3cc76c9b1e973f8"
    },
    {
        "title": "斗破苍穹496商讨（09",
        "url": "https://xiongod.github.io/dpcq2/0496.m4a",
        "duration": "",
        "published": "2024-06-03",
        "createTime": "",
        "chapter": 496,
        "id": "cbba1a20956945c1bed298068df2fb87"
    },
    {
        "title": "斗破苍穹497安顿萧家（10",
        "url": "https://xiongod.github.io/dpcq2/0497.m4a",
        "duration": "",
        "published": "2024-06-03",
        "createTime": "",
        "chapter": 497,
        "id": "e2e473da5a4b4f21b14b1d23f0e4696c"
    },
    {
        "title": "斗破苍穹498雪魅（10",
        "url": "https://xiongod.github.io/dpcq2/0498.m4a",
        "duration": "",
        "published": "2024-06-03",
        "createTime": "",
        "chapter": 498,
        "id": "41bed96600864067bf7e681e01939985"
    },
    {
        "title": "斗破苍穹499见面（10",
        "url": "https://xiongod.github.io/dpcq2/0499.m4a",
        "duration": "",
        "published": "2024-06-03",
        "createTime": "",
        "chapter": 499,
        "id": "607d54ea69734c1cb9b0af13da541e39"
    },
    {
        "title": "斗破苍穹500各大势力会谈（10",
        "url": "https://xiongod.github.io/dpcq2/0500.m4a",
        "duration": "",
        "published": "2024-06-03",
        "createTime": "",
        "chapter": 500,
        "id": "bce585c492cd4dd98a81e5928219b469"
    },
    {
        "title": "斗破苍穹501婚礼阴谋（10",
        "url": "https://xiongod.github.io/dpcq2/0501.m4a",
        "duration": "",
        "published": "2024-06-03",
        "createTime": "",
        "chapter": 501,
        "id": "4553d39809774f08a0067e515a9649ed"
    },
    {
        "title": "斗破苍穹502（10",
        "url": "https://xiongod.github.io/dpcq2/0502.m4a",
        "duration": "",
        "published": "2024-06-03",
        "createTime": "",
        "chapter": 502,
        "id": "07118f8a3a014a0e82a7116cc45bd3d7"
    },
    {
        "title": "斗破苍穹503夜谈（10",
        "url": "https://xiongod.github.io/dpcq2/0503.m4a",
        "duration": "",
        "published": "2024-06-03",
        "createTime": "",
        "chapter": 503,
        "id": "f31bb45c88714009a5d313923d624230"
    },
    {
        "title": "斗破苍穹504混元塑骨丹，治疗（10",
        "url": "https://xiongod.github.io/dpcq2/0504.m4a",
        "duration": "",
        "published": "2024-06-03",
        "createTime": "",
        "chapter": 504,
        "id": "6800e9b4be1047d19c9516fcd777a34a"
    },
    {
        "title": "斗破苍穹505大战来临！（10",
        "url": "https://xiongod.github.io/dpcq2/0505.m4a",
        "duration": "",
        "published": "2024-06-03",
        "createTime": "",
        "chapter": 505,
        "id": "fbac7afa316e4d2dbd75364a688e1cf1"
    },
    {
        "title": "斗破苍穹506大婚之日（10",
        "url": "https://xiongod.github.io/dpcq2/0506.m4a",
        "duration": "",
        "published": "2024-06-03",
        "createTime": "",
        "chapter": 506,
        "id": "3c956aaf8bbe459dbffefaa3e7551ce0"
    },
    {
        "title": "斗破苍穹507十招之战（10",
        "url": "https://xiongod.github.io/dpcq2/0507.m4a",
        "duration": "",
        "published": "2024-06-03",
        "createTime": "",
        "chapter": 507,
        "id": "7062de5255f74148b83f5a35a4288d08"
    },
    {
        "title": "斗破苍穹508战古河（10",
        "url": "https://xiongod.github.io/dpcq2/0508.m4a",
        "duration": "",
        "published": "2024-06-03",
        "createTime": "",
        "chapter": 508,
        "id": "d011e630d4c341aab3893a1c18814560"
    },
    {
        "title": "斗破苍穹509古河败（10",
        "url": "https://xiongod.github.io/dpcq2/0509.m4a",
        "duration": "",
        "published": "2024-06-03",
        "createTime": "",
        "chapter": 509,
        "id": "3e9b3b009e1842639f2bb157b193a5b1"
    },
    {
        "title": "斗破苍穹510决战，云岚宗！云山！（10",
        "url": "https://xiongod.github.io/dpcq2/0510.m4a",
        "duration": "",
        "published": "2024-06-03",
        "createTime": "",
        "chapter": 510,
        "id": "14dfe96f198e48b8a4a23a60bf5090c1"
    },
    {
        "title": "斗破苍穹511焰分噬浪尺vs大悲撕风手！（10",
        "url": "https://xiongod.github.io/dpcq2/0511.m4a",
        "duration": "",
        "published": "2024-06-03",
        "createTime": "",
        "chapter": 511,
        "id": "8d156376a0a24d56af65645302d72f3b"
    },
    {
        "title": "斗破苍穹512鹜护法（10",
        "url": "https://xiongod.github.io/dpcq2/0512.m4a",
        "duration": "",
        "published": "2024-06-03",
        "createTime": "",
        "chapter": 512,
        "id": "7d958a72dc4949a8bcfd4f2b27023deb"
    },
    {
        "title": "斗破苍穹513开山印（10",
        "url": "https://xiongod.github.io/dpcq2/0513.m4a",
        "duration": "",
        "published": "2024-06-03",
        "createTime": "",
        "chapter": 513,
        "id": "ded5fc4aca4d4279b0c4a1280959ed3d"
    },
    {
        "title": "斗破苍穹514底牌，三色火莲爆发！（10",
        "url": "https://xiongod.github.io/dpcq2/0514.m4a",
        "duration": "",
        "published": "2024-06-03",
        "createTime": "",
        "chapter": 514,
        "id": "c7d5fe5b5ee14ba088374af797d33b6c"
    },
    {
        "title": "斗破苍穹515杀云山（10",
        "url": "https://xiongod.github.io/dpcq2/0515.m4a",
        "duration": "",
        "published": "2024-06-03",
        "createTime": "",
        "chapter": 515,
        "id": "437ba894f13145fda7b0a028ff4be89f"
    },
    {
        "title": "斗破苍穹516（10",
        "url": "https://xiongod.github.io/dpcq2/0516.m4a",
        "duration": "",
        "published": "2024-06-03",
        "createTime": "",
        "chapter": 516,
        "id": "15b483e8906f49388dfa9f16e81475a1"
    },
    {
        "title": "斗破苍穹517纳兰嫣然再现（10",
        "url": "https://xiongod.github.io/dpcq2/0517.m4a",
        "duration": "",
        "published": "2024-06-03",
        "createTime": "",
        "chapter": 517,
        "id": "c6454821861b445ba1c16b94d569a33d"
    },
    {
        "title": "斗破苍穹518斗宗大战（10",
        "url": "https://xiongod.github.io/dpcq2/0518.m4a",
        "duration": "",
        "published": "2024-06-03",
        "createTime": "",
        "chapter": 518,
        "id": "10a75f811e164a69905fa749651bf35b"
    },
    {
        "title": "斗破苍穹519被捕（10",
        "url": "https://xiongod.github.io/dpcq2/0519.m4a",
        "duration": "",
        "published": "2024-06-03",
        "createTime": "",
        "chapter": 519,
        "id": "d311c4962a464102ad22b971664fef33"
    },
    {
        "title": "斗破苍穹520痛苦（10",
        "url": "https://xiongod.github.io/dpcq2/0520.m4a",
        "duration": "",
        "published": "2024-06-03",
        "createTime": "",
        "chapter": 520,
        "id": "07859ab47c27424c90a58e54f0abadb1"
    },
    {
        "title": "斗破苍穹521云岚宗结局（10",
        "url": "https://xiongod.github.io/dpcq2/0521.m4a",
        "duration": "",
        "published": "2024-06-03",
        "createTime": "",
        "chapter": 521,
        "id": "6d95891784ae40a393a546afb3487a2d"
    },
    {
        "title": "斗破苍穹522落幕（10",
        "url": "https://xiongod.github.io/dpcq2/0522.m4a",
        "duration": "",
        "published": "2024-06-03",
        "createTime": "",
        "chapter": 522,
        "id": "25c3c8aaedde4c7dadbf93e63e0e2c3e"
    },
    {
        "title": "斗破苍穹523形势（10",
        "url": "https://xiongod.github.io/dpcq2/0523.m4a",
        "duration": "",
        "published": "2024-06-03",
        "createTime": "",
        "chapter": 523,
        "id": "4543aeb399cb40c9a119d9f15bfef38a"
    },
    {
        "title": "斗破苍穹524宗门大会（10",
        "url": "https://xiongod.github.io/dpcq2/0524.m4a",
        "duration": "",
        "published": "2024-06-03",
        "createTime": "",
        "chapter": 524,
        "id": "7d3cd3fa8a7f43ee836bd4ac03a4f266"
    },
    {
        "title": "斗破苍穹525药老所留（10",
        "url": "https://xiongod.github.io/dpcq2/0525.m4a",
        "duration": "",
        "published": "2024-06-03",
        "createTime": "",
        "chapter": 525,
        "id": "c36edaaf2baf45c1be5f9cd194d5f12f"
    },
    {
        "title": "斗破苍穹526势力雏形（10",
        "url": "https://xiongod.github.io/dpcq2/0526.m4a",
        "duration": "",
        "published": "2024-06-03",
        "createTime": "",
        "chapter": 526,
        "id": "66705736ed7e44d4a5436f069f0b1e22"
    },
    {
        "title": "斗破苍穹527云韵离开（10",
        "url": "https://xiongod.github.io/dpcq2/0527.m4a",
        "duration": "",
        "published": "2024-06-03",
        "createTime": "",
        "chapter": 527,
        "id": "49f8d6b8407a4bef89bcec3f1ad72efb"
    },
    {
        "title": "斗破苍穹528（10",
        "url": "https://xiongod.github.io/dpcq2/0528.m4a",
        "duration": "",
        "published": "2024-06-03",
        "createTime": "",
        "chapter": 528,
        "id": "ccf7af7f703b42eeb91cbfba74fae270"
    },
    {
        "title": "斗破苍穹529（麦克风电源烧了返修。最后3集，1天1更，看周一能不能修好）",
        "url": "https://xiongod.github.io/dpcq2/0529.m4a",
        "duration": "",
        "published": "2024-06-03",
        "createTime": "",
        "chapter": 529,
        "id": "84595f6f38c1496d82ed95aee9a0a9ac"
    },
    {
        "title": "斗破苍穹530（10",
        "url": "https://xiongod.github.io/dpcq2/0530.m4a",
        "duration": "",
        "published": "2024-06-03",
        "createTime": "",
        "chapter": 530,
        "id": "f806866d11eb4bd880946da39af577bf"
    },
    {
        "title": "斗破苍穹531（10",
        "url": "https://xiongod.github.io/dpcq2/0531.m4a",
        "duration": "",
        "published": "2024-06-03",
        "createTime": "",
        "chapter": 531,
        "id": "8e80f661242444fca70717eabfeb662f"
    },
    {
        "title": "斗破苍穹532遇故（10",
        "url": "https://xiongod.github.io/dpcq2/0532.m4a",
        "duration": "",
        "published": "2024-06-03",
        "createTime": "",
        "chapter": 532,
        "id": "b0c4baad3c9d46e2b574336dd6aa5a15"
    },
    {
        "title": "斗破苍穹533古怪的山谷（10",
        "url": "https://xiongod.github.io/dpcq2/0533.m4a",
        "duration": "",
        "published": "2024-06-03",
        "createTime": "",
        "chapter": 533,
        "id": "857042a95f5045ddb352370bd79daf9e"
    },
    {
        "title": "斗破苍穹534神秘黑影（10",
        "url": "https://xiongod.github.io/dpcq2/0534.m4a",
        "duration": "",
        "published": "2024-06-03",
        "createTime": "",
        "chapter": 534,
        "id": "7ced4a0ca8dc449284d207eb829f6e8c"
    },
    {
        "title": "斗破苍穹535小医仙（10",
        "url": "https://xiongod.github.io/dpcq2/0535.m4a",
        "duration": "",
        "published": "2024-06-03",
        "createTime": "",
        "chapter": 535,
        "id": "5e25af2925044e21aa0b01bba700f630"
    },
    {
        "title": "斗破苍穹536闭关前准备（10",
        "url": "https://xiongod.github.io/dpcq2/0536.m4a",
        "duration": "",
        "published": "2024-06-03",
        "createTime": "",
        "chapter": 536,
        "id": "b7707679600b4501beddc560d38600e9"
    },
    {
        "title": "斗破苍穹537赫家（10",
        "url": "https://xiongod.github.io/dpcq2/0537.m4a",
        "duration": "",
        "published": "2024-06-03",
        "createTime": "",
        "chapter": 537,
        "id": "01270a97874243a09384e09666942b7d"
    },
    {
        "title": "斗破苍穹538援手（10",
        "url": "https://xiongod.github.io/dpcq2/0538.m4a",
        "duration": "",
        "published": "2024-06-03",
        "createTime": "",
        "chapter": 538,
        "id": "cf75b1255b434e898e3001e7efe7e054"
    },
    {
        "title": "斗破苍穹539（10",
        "url": "https://xiongod.github.io/dpcq2/0539.m4a",
        "duration": "",
        "published": "2024-06-03",
        "createTime": "",
        "chapter": 539,
        "id": "921ef4f3c36141e7981068c2e158233f"
    },
    {
        "title": "斗破苍穹540闭关变动（10",
        "url": "https://xiongod.github.io/dpcq2/0540.m4a",
        "duration": "",
        "published": "2024-06-03",
        "createTime": "",
        "chapter": 540,
        "id": "e1991e59236944ccb368a73e62ae06ae"
    },
    {
        "title": "斗破苍穹541晋升斗皇（10",
        "url": "https://xiongod.github.io/dpcq2/0541.m4a",
        "duration": "",
        "published": "2024-06-03",
        "createTime": "",
        "chapter": 541,
        "id": "f7d453e3f8e540efa200f6069896a857"
    },
    {
        "title": "斗破苍穹542",
        "url": "https://xiongod.github.io/dpcq2/0542.m4a",
        "duration": "",
        "published": "2024-06-03",
        "createTime": "",
        "chapter": 542,
        "id": "c7d6cc7ffa3341909fb7013d2807575d"
    },
    {
        "title": "斗破苍穹543加玛帝国大乱（10",
        "url": "https://xiongod.github.io/dpcq2/0543.m4a",
        "duration": "",
        "published": "2024-06-03",
        "createTime": "",
        "chapter": 543,
        "id": "8abdd100fdae4ae8aa551402065f34e9"
    },
    {
        "title": "斗破苍穹544毒宗，金雁宗，慕兰谷（10",
        "url": "https://xiongod.github.io/dpcq2/0544.m4a",
        "duration": "",
        "published": "2024-06-03",
        "createTime": "",
        "chapter": 544,
        "id": "ddccd104817542699df53cbedc08b1f4"
    },
    {
        "title": "斗破苍穹545斗破苍穹545月媚（10",
        "url": "https://xiongod.github.io/dpcq2/0545.m4a",
        "duration": "",
        "published": "2024-06-03",
        "createTime": "",
        "chapter": 545,
        "id": "36ede24fd25d485997ff99e3c0523bf8"
    },
    {
        "title": "斗破苍穹546情势，黑山要塞（10",
        "url": "https://xiongod.github.io/dpcq2/0546.m4a",
        "duration": "",
        "published": "2024-06-03",
        "createTime": "",
        "chapter": 546,
        "id": "a90a1c055b2d49558d8f1a173a5e4585"
    },
    {
        "title": "斗破苍穹547三兽蛮荒决（10",
        "url": "https://xiongod.github.io/dpcq2/0547.m4a",
        "duration": "",
        "published": "2024-06-03",
        "createTime": "",
        "chapter": 547,
        "id": "c6309170ad384ed2959184ea91fb7981"
    },
    {
        "title": "斗破苍穹548迎战慕兰三老（10",
        "url": "https://xiongod.github.io/dpcq2/0548.m4a",
        "duration": "",
        "published": "2024-06-03",
        "createTime": "",
        "chapter": 548,
        "id": "21d2272c3f7c42fdbbd32d94c69f1861"
    },
    {
        "title": "斗破苍穹549破绽（10",
        "url": "https://xiongod.github.io/dpcq2/0549.m4a",
        "duration": "",
        "published": "2024-06-03",
        "createTime": "",
        "chapter": 549,
        "id": "4c9156cc1fd046f39d34a9e1300588dc"
    },
    {
        "title": "斗破苍穹550三千雷，骗局（10",
        "url": "https://xiongod.github.io/dpcq2/0550.m4a",
        "duration": "",
        "published": "2024-06-03",
        "createTime": "",
        "chapter": 550,
        "id": "cc64ad2be42f4801aa367eb9da10cdc5"
    },
    {
        "title": "斗破苍穹551鹰啼，毒宗宗主（10",
        "url": "https://xiongod.github.io/dpcq2/0551.m4a",
        "duration": "",
        "published": "2024-06-03",
        "createTime": "",
        "chapter": 551,
        "id": "91932d7b9a694fc8b1b2c4cc0e628d15"
    },
    {
        "title": "斗破苍穹552身法较技（10",
        "url": "https://xiongod.github.io/dpcq2/0552.m4a",
        "duration": "",
        "published": "2024-06-03",
        "createTime": "",
        "chapter": 552,
        "id": "b6ee4db28bd840fa94d808b39b40f4e1"
    },
    {
        "title": "斗破苍穹553三色火莲，爆！（10",
        "url": "https://xiongod.github.io/dpcq2/0553.m4a",
        "duration": "",
        "published": "2024-06-03",
        "createTime": "",
        "chapter": 553,
        "id": "56430e09b1ed4236b440ffa879f4901a"
    },
    {
        "title": "斗破苍穹554物是人非（11",
        "url": "https://xiongod.github.io/dpcq2/0554.m4a",
        "duration": "",
        "published": "2024-06-03",
        "createTime": "",
        "chapter": 554,
        "id": "40f28c7280104edaba4e7673f6d1c768"
    },
    {
        "title": "斗破苍穹555大战休止（11",
        "url": "https://xiongod.github.io/dpcq2/0555.m4a",
        "duration": "",
        "published": "2024-06-03",
        "createTime": "",
        "chapter": 555,
        "id": "ec4ff0dbc5b8494888c53e30182bc747"
    },
    {
        "title": "斗破苍穹556毒丹之法（11",
        "url": "https://xiongod.github.io/dpcq2/0556.m4a",
        "duration": "",
        "published": "2024-06-03",
        "createTime": "",
        "chapter": 556,
        "id": "4193654ed4df47ba8f970c79a77fa18e"
    },
    {
        "title": "斗破苍穹557进入蛇人族（11",
        "url": "https://xiongod.github.io/dpcq2/0557.m4a",
        "duration": "",
        "published": "2024-06-03",
        "createTime": "",
        "chapter": 557,
        "id": "b955b1c7ad9c4c98822844da06c92ea7"
    },
    {
        "title": "斗破苍穹558蛇人族，怀孕（11",
        "url": "https://xiongod.github.io/dpcq2/0558.m4a",
        "duration": "",
        "published": "2024-06-03",
        "createTime": "",
        "chapter": 558,
        "id": "7f985a25d62144e9999babcde64ddb6d"
    },
    {
        "title": "斗破苍穹559秘法三等（11",
        "url": "https://xiongod.github.io/dpcq2/0559.m4a",
        "duration": "",
        "published": "2024-06-03",
        "createTime": "",
        "chapter": 559,
        "id": "ca21d93d962649f980fe66642b0c49f9"
    },
    {
        "title": "斗破苍穹560摩擦（11",
        "url": "https://xiongod.github.io/dpcq2/0560.m4a",
        "duration": "",
        "published": "2024-06-03",
        "createTime": "",
        "chapter": 560,
        "id": "f33bf2c6540543dfb4c8f11caa3af4eb"
    },
    {
        "title": "斗破苍穹561调养，行动（11",
        "url": "https://xiongod.github.io/dpcq2/0561.m4a",
        "duration": "",
        "published": "2024-06-03",
        "createTime": "",
        "chapter": 561,
        "id": "556901a544a742c6adf7238f15b9b754"
    },
    {
        "title": "斗破苍穹562暗杀！（11",
        "url": "https://xiongod.github.io/dpcq2/0562.m4a",
        "duration": "",
        "published": "2024-06-03",
        "createTime": "",
        "chapter": 562,
        "id": "46831d38be10429b9b967056a8796e3a"
    },
    {
        "title": "斗破苍穹563以寡敌众（11",
        "url": "https://xiongod.github.io/dpcq2/0563.m4a",
        "duration": "",
        "published": "2024-06-03",
        "createTime": "",
        "chapter": 563,
        "id": "eb2fd28567c54653a45ff4fe1de4594b"
    },
    {
        "title": "斗破苍穹564天雁九行翼（11",
        "url": "https://xiongod.github.io/dpcq2/0564.m4a",
        "duration": "",
        "published": "2024-06-03",
        "createTime": "",
        "chapter": 564,
        "id": "7e61fc9181a04f03aac757deb81d34de"
    },
    {
        "title": "斗破苍穹565云山之上，薰儿！（11",
        "url": "https://xiongod.github.io/dpcq2/0565.m4a",
        "duration": "",
        "published": "2024-06-03",
        "createTime": "",
        "chapter": 565,
        "id": "8d1e02b1d5574881b4833236a0f7def5"
    },
    {
        "title": "斗破苍穹566招揽古河（11",
        "url": "https://xiongod.github.io/dpcq2/0566.m4a",
        "duration": "",
        "published": "2024-06-03",
        "createTime": "",
        "chapter": 566,
        "id": "91fffbdaa8614339a63aff06bff5a028"
    },
    {
        "title": "斗破苍穹567光头大统领（11",
        "url": "https://xiongod.github.io/dpcq2/0567.m4a",
        "duration": "",
        "published": "2024-06-03",
        "createTime": "",
        "chapter": 567,
        "id": "df98ab6f666d421fb89014854570f0ae"
    },
    {
        "title": "斗破苍穹568赶往出云！（11",
        "url": "https://xiongod.github.io/dpcq2/0568.m4a",
        "duration": "",
        "published": "2024-06-03",
        "createTime": "",
        "chapter": 568,
        "id": "aa4acc6d7d61420b9bb4db24029c8c42"
    },
    {
        "title": "斗破苍穹569万蝎门（11",
        "url": "https://xiongod.github.io/dpcq2/0569.m4a",
        "duration": "",
        "published": "2024-06-03",
        "createTime": "",
        "chapter": 569,
        "id": "d4da2895f4dc4856a712387e91710a84"
    },
    {
        "title": "斗破苍穹570蜈崖（11",
        "url": "https://xiongod.github.io/dpcq2/0570.m4a",
        "duration": "",
        "published": "2024-06-03",
        "createTime": "",
        "chapter": 570,
        "id": "8bab67d7a6bc4198a7256875b558c285"
    },
    {
        "title": "斗破苍穹571凶险（11",
        "url": "https://xiongod.github.io/dpcq2/0571.m4a",
        "duration": "",
        "published": "2024-06-03",
        "createTime": "",
        "chapter": 571,
        "id": "eb6780720b934e63827f1039b4600c65"
    },
    {
        "title": "斗破苍穹572门派大战（11",
        "url": "https://xiongod.github.io/dpcq2/0572.m4a",
        "duration": "",
        "published": "2024-06-03",
        "createTime": "",
        "chapter": 572,
        "id": "802b633a23504509aa2711f30df12b8e"
    },
    {
        "title": "斗破苍穹573蜈崖死（11",
        "url": "https://xiongod.github.io/dpcq2/0573.m4a",
        "duration": "",
        "published": "2024-06-03",
        "createTime": "",
        "chapter": 573,
        "id": "ba582f89a371429b8a5b05979e7465c0"
    },
    {
        "title": "斗破苍穹574四翼天魔蝎（11",
        "url": "https://xiongod.github.io/dpcq2/0574.m4a",
        "duration": "",
        "published": "2024-06-03",
        "createTime": "",
        "chapter": 574,
        "id": "a150062679464bcbbc0a74e0f591d9f1"
    },
    {
        "title": "斗破苍穹575铁护法（11",
        "url": "https://xiongod.github.io/dpcq2/0575.m4a",
        "duration": "",
        "published": "2024-06-03",
        "createTime": "",
        "chapter": 575,
        "id": "719c18f3ba7940fe858d95ee1623756e"
    },
    {
        "title": "斗破苍穹576斗宗大爆发（11",
        "url": "https://xiongod.github.io/dpcq2/0576.m4a",
        "duration": "",
        "published": "2024-06-03",
        "createTime": "",
        "chapter": 576,
        "id": "8b1b795de9aa4fdf9fe61b3f60b0e257"
    },
    {
        "title": "斗破苍穹577蝎山死（11",
        "url": "https://xiongod.github.io/dpcq2/0577.m4a",
        "duration": "",
        "published": "2024-06-03",
        "createTime": "",
        "chapter": 577,
        "id": "8c9df88612b143a6bed3b3b260bbaf13"
    },
    {
        "title": "斗破苍穹578毁魂袋（11",
        "url": "https://xiongod.github.io/dpcq2/0578.m4a",
        "duration": "",
        "published": "2024-06-03",
        "createTime": "",
        "chapter": 578,
        "id": "a188917a39664f0f806b6bf3a9ed70ee"
    },
    {
        "title": "斗破苍穹579狼狈的铁护法（11",
        "url": "https://xiongod.github.io/dpcq2/0579.m4a",
        "duration": "",
        "published": "2024-06-03",
        "createTime": "",
        "chapter": 579,
        "id": "d233e9238ac24f4798bf9ef8e5c98b0e"
    },
    {
        "title": "斗破苍穹580擒获！（11",
        "url": "https://xiongod.github.io/dpcq2/0580.m4a",
        "duration": "",
        "published": "2024-06-03",
        "createTime": "",
        "chapter": 580,
        "id": "1c5f7a1fe672410baa6a69b7cb2bc711"
    },
    {
        "title": "斗破苍穹581魔毒斑（11",
        "url": "https://xiongod.github.io/dpcq2/0581.m4a",
        "duration": "",
        "published": "2024-06-03",
        "createTime": "",
        "chapter": 581,
        "id": "e3ca88fb5f8d4ce486ae103df7e6f321"
    },
    {
        "title": "斗破苍穹582石池（11",
        "url": "https://xiongod.github.io/dpcq2/0582.m4a",
        "duration": "",
        "published": "2024-06-03",
        "createTime": "",
        "chapter": 582,
        "id": "4766c02c87dd486f80b794a6b2d1aad7"
    },
    {
        "title": "斗破苍穹583封印魔毒斑（11",
        "url": "https://xiongod.github.io/dpcq2/0583.m4a",
        "duration": "",
        "published": "2024-06-03",
        "createTime": "",
        "chapter": 583,
        "id": "264080d84ef24653b3d774bcfcae3a64"
    },
    {
        "title": "斗破苍穹584二星斗皇，净莲妖火（11",
        "url": "https://xiongod.github.io/dpcq2/0584.m4a",
        "duration": "",
        "published": "2024-06-03",
        "createTime": "",
        "chapter": 584,
        "id": "dfe0e0607bd24b54a398fee688135f40"
    },
    {
        "title": "斗破苍穹585魂殿情报（11",
        "url": "https://xiongod.github.io/dpcq2/0585.m4a",
        "duration": "",
        "published": "2024-06-03",
        "createTime": "",
        "chapter": 585,
        "id": "fcc4a2b6c2c841fe9814a470dae1fe29"
    },
    {
        "title": "斗破苍穹586赶往黑角域（11",
        "url": "https://xiongod.github.io/dpcq2/0586.m4a",
        "duration": "",
        "published": "2024-06-03",
        "createTime": "",
        "chapter": 586,
        "id": "65e804a981394332a0189ff39a16f29c"
    },
    {
        "title": "斗破苍穹587路遇（11",
        "url": "https://xiongod.github.io/dpcq2/0587.m4a",
        "duration": "",
        "published": "2024-06-03",
        "createTime": "",
        "chapter": 587,
        "id": "f4cbfa5febf448b1bfcd5f93fd09b0cb"
    },
    {
        "title": "斗破苍穹588血剑吴昊（11",
        "url": "https://xiongod.github.io/dpcq2/0588.m4a",
        "duration": "",
        "published": "2024-06-03",
        "createTime": "",
        "chapter": 588,
        "id": "ddc47d3eee574ed296edeebcd819a9fc"
    },
    {
        "title": "斗破苍穹589鹰爪老人（11",
        "url": "https://xiongod.github.io/dpcq2/0589.m4a",
        "duration": "",
        "published": "2024-06-03",
        "createTime": "",
        "chapter": 589,
        "id": "bf87809147e3432ab3493cd8b16d250e"
    },
    {
        "title": "斗破苍穹590萧门，萧炎（11",
        "url": "https://xiongod.github.io/dpcq2/0590.m4a",
        "duration": "",
        "published": "2024-06-03",
        "createTime": "",
        "chapter": 590,
        "id": "d741cf42bead49799e5438c2b5ae061b"
    },
    {
        "title": "斗破苍穹591一个不留 （11",
        "url": "https://xiongod.github.io/dpcq2/0591.m4a",
        "duration": "",
        "published": "2024-06-03",
        "createTime": "",
        "chapter": 591,
        "id": "c166366a71d4459eb3ecd9377cc68c76"
    },
    {
        "title": "斗破苍穹592进入黑皇城（11",
        "url": "https://xiongod.github.io/dpcq2/0592.m4a",
        "duration": "",
        "published": "2024-06-03",
        "createTime": "",
        "chapter": 592,
        "id": "cd6058f96fac417cb99fdcc4b92c79d7"
    },
    {
        "title": "斗破苍穹593千药坊（11",
        "url": "https://xiongod.github.io/dpcq2/0593.m4a",
        "duration": "",
        "published": "2024-06-03",
        "createTime": "",
        "chapter": 593,
        "id": "4d952b9bf55849f2b9097d20698000a4"
    },
    {
        "title": "斗破苍穹594换丹集会（11",
        "url": "https://xiongod.github.io/dpcq2/0594.m4a",
        "duration": "",
        "published": "2024-06-03",
        "createTime": "",
        "chapter": 594,
        "id": "eb882df0487e4568bfe5f2ac6c8bed19"
    },
    {
        "title": "斗破苍穹595竞价（11",
        "url": "https://xiongod.github.io/dpcq2/0595.m4a",
        "duration": "",
        "published": "2024-06-03",
        "createTime": "",
        "chapter": 595,
        "id": "80e142fd08444456b2f82d72bfd10130"
    },
    {
        "title": "斗破苍穹596得手（11",
        "url": "https://xiongod.github.io/dpcq2/0596.m4a",
        "duration": "",
        "published": "2024-06-03",
        "createTime": "",
        "chapter": 596,
        "id": "36d6b6af83da49829702c5d7bce91a9d"
    },
    {
        "title": "斗破苍穹597菩提化体涎（11",
        "url": "https://xiongod.github.io/dpcq2/0597.m4a",
        "duration": "",
        "published": "2024-06-03",
        "createTime": "",
        "chapter": 597,
        "id": "6d664d85e1684c33937cbbed2282c852"
    },
    {
        "title": "斗破苍穹598黒皇阁（11",
        "url": "https://xiongod.github.io/dpcq2/0598.m4a",
        "duration": "",
        "published": "2024-06-03",
        "createTime": "",
        "chapter": 598,
        "id": "cbf3265b472849178c1a5b92190aacb5"
    },
    {
        "title": "斗破苍穹599白衣人莫崖（11",
        "url": "https://xiongod.github.io/dpcq2/0599.m4a",
        "duration": "",
        "published": "2024-06-03",
        "createTime": "",
        "chapter": 599,
        "id": "82062b25092d4e8386413780165912bc"
    },
    {
        "title": "斗破苍穹600强者云集（11",
        "url": "https://xiongod.github.io/dpcq2/0600.m4a",
        "duration": "",
        "published": "2024-06-03",
        "createTime": "",
        "chapter": 600,
        "id": "8dcf95a8aad945828b1f1cd8a15dac67"
    },
    {
        "title": "斗破苍穹601二女暗手（11",
        "url": "https://xiongod.github.io/dpcq2/0601.m4a",
        "duration": "",
        "published": "2024-06-03",
        "createTime": "",
        "chapter": 601,
        "id": "a06e06dc717d415a9801848a25bf8147"
    },
    {
        "title": "斗破苍穹602炼制破宗丹（10",
        "url": "https://xiongod.github.io/dpcq2/0602.m4a",
        "duration": "",
        "published": "2024-06-03",
        "createTime": "",
        "chapter": 602,
        "id": "87ad87aa25bd41f3aaf04bdec6e29826"
    },
    {
        "title": "斗破苍穹603动静，震慑（11",
        "url": "https://xiongod.github.io/dpcq2/0603.m4a",
        "duration": "",
        "published": "2024-06-03",
        "createTime": "",
        "chapter": 603,
        "id": "a4222a90986c41e6a48d92179eb98595"
    },
    {
        "title": "斗破苍穹604拍卖开场（11",
        "url": "https://xiongod.github.io/dpcq2/0604.m4a",
        "duration": "",
        "published": "2024-06-03",
        "createTime": "",
        "chapter": 604,
        "id": "6fa1e52b572d47a4a9f484e7bd62e6f2"
    },
    {
        "title": "斗破苍穹605拍卖！（11",
        "url": "https://xiongod.github.io/dpcq2/0605.m4a",
        "duration": "",
        "published": "2024-06-03",
        "createTime": "",
        "chapter": 605,
        "id": "abf4399faf5844bbb32d3bb8db8de30f"
    },
    {
        "title": "斗破苍穹606六合游身尺（11",
        "url": "https://xiongod.github.io/dpcq2/0606.m4a",
        "duration": "",
        "published": "2024-06-03",
        "createTime": "",
        "chapter": 606,
        "id": "b17497593d8b4496812bcbac34f6b7e3"
    },
    {
        "title": "斗破苍穹607魔兽干尸（11",
        "url": "https://xiongod.github.io/dpcq2/0607.m4a",
        "duration": "",
        "published": "2024-06-03",
        "createTime": "",
        "chapter": 607,
        "id": "7729b276db5f4816a3129953a58db671"
    },
    {
        "title": "斗破苍穹608以物换物（11",
        "url": "https://xiongod.github.io/dpcq2/0608.m4a",
        "duration": "",
        "published": "2024-06-03",
        "createTime": "",
        "chapter": 608,
        "id": "69a4bb45c1164c00ae98487a40b19bfe"
    },
    {
        "title": "斗破苍穹609斗破苍穹609菩提化体涎（11",
        "url": "https://xiongod.github.io/dpcq2/0609.m4a",
        "duration": "",
        "published": "2024-06-03",
        "createTime": "",
        "chapter": 609,
        "id": "07f134ef065e4300af63764d5610cc67"
    },
    {
        "title": "斗破苍穹610各显本钱（11",
        "url": "https://xiongod.github.io/dpcq2/0610.m4a",
        "duration": "",
        "published": "2024-06-03",
        "createTime": "",
        "chapter": 610,
        "id": "a15c4e7bbcc041938b9fb6e97e4fa951"
    },
    {
        "title": "斗破苍穹611鹰山老人（11",
        "url": "https://xiongod.github.io/dpcq2/0611.m4a",
        "duration": "",
        "published": "2024-06-03",
        "createTime": "",
        "chapter": 611,
        "id": "65d861af7a904d1f97fdab50d37e1a49"
    },
    {
        "title": "斗破苍穹612见面（11",
        "url": "https://xiongod.github.io/dpcq2/0612.m4a",
        "duration": "",
        "published": "2024-06-03",
        "createTime": "",
        "chapter": 612,
        "id": "e5852ee61ede4dab9d7f83d66e434e89"
    },
    {
        "title": "斗破苍穹613相谈（11",
        "url": "https://xiongod.github.io/dpcq2/0613.m4a",
        "duration": "",
        "published": "2024-06-03",
        "createTime": "",
        "chapter": 613,
        "id": "dd6fbac5439143ecb95772e5f8fb164f"
    },
    {
        "title": "斗破苍穹614分尸（11",
        "url": "https://xiongod.github.io/dpcq2/0614.m4a",
        "duration": "",
        "published": "2024-06-03",
        "createTime": "",
        "chapter": 614,
        "id": "708e550d30a44b0ab1228e1a8b80f1f2"
    },
    {
        "title": "斗破苍穹615青红血液（12",
        "url": "https://xiongod.github.io/dpcq2/0615.m4a",
        "duration": "",
        "published": "2024-06-03",
        "createTime": "",
        "chapter": 615,
        "id": "c8c518e0dd384ff08a370fff1b79ad26"
    },
    {
        "title": "斗破苍穹616心火种子（12",
        "url": "https://xiongod.github.io/dpcq2/0616.m4a",
        "duration": "",
        "published": "2024-06-03",
        "createTime": "",
        "chapter": 616,
        "id": "cd2a4215e49f45b797d2ce00f552afc7"
    },
    {
        "title": "斗破苍穹617尾随（12",
        "url": "https://xiongod.github.io/dpcq2/0617.m4a",
        "duration": "",
        "published": "2024-06-03",
        "createTime": "",
        "chapter": 617,
        "id": "d90ef6f7b47d4779b2faf1c03d7e79b7"
    },
    {
        "title": "斗破苍穹618灵魂分身（12",
        "url": "https://xiongod.github.io/dpcq2/0618.m4a",
        "duration": "",
        "published": "2024-06-03",
        "createTime": "",
        "chapter": 618,
        "id": "c7d6fd4babba44f5a53d2121fb550df5"
    },
    {
        "title": "斗破苍穹619果然是你（12",
        "url": "https://xiongod.github.io/dpcq2/0619.m4a",
        "duration": "",
        "published": "2024-06-03",
        "createTime": "",
        "chapter": 619,
        "id": "69636fdbbf9440418a6592990633a7a9"
    },
    {
        "title": "斗破苍穹620同门再见（12",
        "url": "https://xiongod.github.io/dpcq2/0620.m4a",
        "duration": "",
        "published": "2024-06-03",
        "createTime": "",
        "chapter": 620,
        "id": "804fc6f975534aa7bfe44545b48ef228"
    },
    {
        "title": "斗破苍穹621局势转变（12",
        "url": "https://xiongod.github.io/dpcq2/0621.m4a",
        "duration": "",
        "published": "2024-06-03",
        "createTime": "",
        "chapter": 621,
        "id": "bed8101f88a6458aa7420c4d7903d2c1"
    },
    {
        "title": "斗破苍穹622化生火（12",
        "url": "https://xiongod.github.io/dpcq2/0622.m4a",
        "duration": "",
        "published": "2024-06-03",
        "createTime": "",
        "chapter": 622,
        "id": "c2ed2dd3589241dcb5f59924acb171bd"
    },
    {
        "title": "斗破苍穹623星空火凰（12",
        "url": "https://xiongod.github.io/dpcq2/0623.m4a",
        "duration": "",
        "published": "2024-06-03",
        "createTime": "",
        "chapter": 623,
        "id": "d719fb40cedc4404919ceaa6828f9ca3"
    },
    {
        "title": "斗破苍穹624收服化生火（12",
        "url": "https://xiongod.github.io/dpcq2/0624.m4a",
        "duration": "",
        "published": "2024-06-03",
        "createTime": "",
        "chapter": 624,
        "id": "cefd391fc1c940e09d0fce1597f47bd0"
    },
    {
        "title": "斗破苍穹625暴走的紫研（12",
        "url": "https://xiongod.github.io/dpcq2/0625.m4a",
        "duration": "",
        "published": "2024-06-03",
        "createTime": "",
        "chapter": 625,
        "id": "235ac6bdbd424b83a9d11d01bf001649"
    },
    {
        "title": "斗破苍穹626喝退莫天行（12",
        "url": "https://xiongod.github.io/dpcq2/0626.m4a",
        "duration": "",
        "published": "2024-06-03",
        "createTime": "",
        "chapter": 626,
        "id": "2b867ea7580346b4a3a78b0f1b35f586"
    },
    {
        "title": "斗破苍穹627离去，变故（12",
        "url": "https://xiongod.github.io/dpcq2/0627.m4a",
        "duration": "",
        "published": "2024-06-03",
        "createTime": "",
        "chapter": 627,
        "id": "724a10a0df0c449fa78e2d68eca4ba82"
    },
    {
        "title": "斗破苍穹628消除隐患（12",
        "url": "https://xiongod.github.io/dpcq2/0628.m4a",
        "duration": "",
        "published": "2024-06-03",
        "createTime": "",
        "chapter": 628,
        "id": "c3a258d4eabb43ed865a5b2f49da482f"
    },
    {
        "title": "斗破苍穹629欣蓝（12",
        "url": "https://xiongod.github.io/dpcq2/0629.m4a",
        "duration": "",
        "published": "2024-06-03",
        "createTime": "",
        "chapter": 629,
        "id": "9f97446b36c04ac9be88d18a4788a6b0"
    },
    {
        "title": "斗破苍穹630见面叙旧（12",
        "url": "https://xiongod.github.io/dpcq2/0630.m4a",
        "duration": "",
        "published": "2024-06-03",
        "createTime": "",
        "chapter": 630,
        "id": "42d9395a6eac4107aa820608d75b9d58"
    },
    {
        "title": "斗破苍穹631异火消息（12",
        "url": "https://xiongod.github.io/dpcq2/0631.m4a",
        "duration": "",
        "published": "2024-06-03",
        "createTime": "",
        "chapter": 631,
        "id": "6618edd254e14411b3b5c9c77186f14b"
    },
    {
        "title": "斗破苍穹632九龙雷罡火（12",
        "url": "https://xiongod.github.io/dpcq2/0632.m4a",
        "duration": "",
        "published": "2024-06-03",
        "createTime": "",
        "chapter": 632,
        "id": "139735dab03640efb57a69221d322a9a"
    },
    {
        "title": "斗破苍穹633三千焱炎火（12",
        "url": "https://xiongod.github.io/dpcq2/0633.m4a",
        "duration": "",
        "published": "2024-06-03",
        "createTime": "",
        "chapter": 633,
        "id": "bdfc28075b8943ce9a3e3b1c873cf09d"
    },
    {
        "title": "斗破苍穹634炼制天雁九行翼（12",
        "url": "https://xiongod.github.io/dpcq2/0634.m4a",
        "duration": "",
        "published": "2024-06-03",
        "createTime": "",
        "chapter": 634,
        "id": "60a942c66496476189b8b8e1fed8c79d"
    },
    {
        "title": "斗破苍穹635霸道的骨翼（12",
        "url": "https://xiongod.github.io/dpcq2/0635.m4a",
        "duration": "",
        "published": "2024-06-03",
        "createTime": "",
        "chapter": 635,
        "id": "aa706f3a627a4b89924c05db98bb43ed"
    },
    {
        "title": "斗破苍穹636一劳永逸（12",
        "url": "https://xiongod.github.io/dpcq2/0636.m4a",
        "duration": "",
        "published": "2024-06-03",
        "createTime": "",
        "chapter": 636,
        "id": "b700b5c5e6f348b1beeec1142657464b"
    },
    {
        "title": "斗破苍穹637魔炎谷强者到来（12",
        "url": "https://xiongod.github.io/dpcq2/0637.m4a",
        "duration": "",
        "published": "2024-06-03",
        "createTime": "",
        "chapter": 637,
        "id": "15ceed3c55014f55aeedcf8c00ba63cd"
    },
    {
        "title": "斗破苍穹638对战地魔老鬼（12",
        "url": "https://xiongod.github.io/dpcq2/0638.m4a",
        "duration": "",
        "published": "2024-06-03",
        "createTime": "",
        "chapter": 638,
        "id": "98fb0f0e607f47af809adba83f8d1c7d"
    },
    {
        "title": "斗破苍穹639惊心动魄（12",
        "url": "https://xiongod.github.io/dpcq2/0639.m4a",
        "duration": "",
        "published": "2024-06-03",
        "createTime": "",
        "chapter": 639,
        "id": "f909a0e1059d49ab9199805288bf9c10"
    },
    {
        "title": "斗破苍穹640疯狂（12",
        "url": "https://xiongod.github.io/dpcq2/0640.m4a",
        "duration": "",
        "published": "2024-06-03",
        "createTime": "",
        "chapter": 640,
        "id": "a49b36dab4c54a738e93b962f3cdc310"
    },
    {
        "title": "斗破苍穹641毁灭火莲（12",
        "url": "https://xiongod.github.io/dpcq2/0641.m4a",
        "duration": "",
        "published": "2024-06-03",
        "createTime": "",
        "chapter": 641,
        "id": "2d7627fcea314a2b97351d0686430fbb"
    },
    {
        "title": "斗破苍穹642千百二老（12",
        "url": "https://xiongod.github.io/dpcq2/0642.m4a",
        "duration": "",
        "published": "2024-06-03",
        "createTime": "",
        "chapter": 642,
        "id": "b0293cc00eb84528b3650516727fc8c1"
    },
    {
        "title": "斗破苍穹643希冀（10",
        "url": "https://xiongod.github.io/dpcq2/0643.m4a",
        "duration": "",
        "published": "2024-06-03",
        "createTime": "",
        "chapter": 643,
        "id": "84e896069f02411b8705829801c258e3"
    },
    {
        "title": "斗破苍穹644失败（10",
        "url": "https://xiongod.github.io/dpcq2/0644.m4a",
        "duration": "",
        "published": "2024-06-03",
        "createTime": "",
        "chapter": 644,
        "id": "ee90eaee54db4269a081f9bac6ea8aef"
    },
    {
        "title": "斗破苍穹645修炼之所（12",
        "url": "https://xiongod.github.io/dpcq2/0645.m4a",
        "duration": "",
        "published": "2024-06-03",
        "createTime": "",
        "chapter": 645,
        "id": "65f114866d394181ad26058cfdec1f02"
    },
    {
        "title": "斗破苍穹646再进塔底（12",
        "url": "https://xiongod.github.io/dpcq2/0646.m4a",
        "duration": "",
        "published": "2024-06-03",
        "createTime": "",
        "chapter": 646,
        "id": "2dd9024fa89349f9b960dd4207e309c0"
    },
    {
        "title": "斗破苍穹647尺法小成（12",
        "url": "https://xiongod.github.io/dpcq2/0647.m4a",
        "duration": "",
        "published": "2024-06-03",
        "createTime": "",
        "chapter": 647,
        "id": "f93426efc33647468d9ff3f8fe18f309"
    },
    {
        "title": "斗破苍穹648神秘骨骸（12",
        "url": "https://xiongod.github.io/dpcq2/0648.m4a",
        "duration": "",
        "published": "2024-06-03",
        "createTime": "",
        "chapter": 648,
        "id": "c05f7838af674da2a66e9240cafcf2bb"
    },
    {
        "title": "斗破苍穹649火焰蜥蜴族（12",
        "url": "https://xiongod.github.io/dpcq2/0649.m4a",
        "duration": "",
        "published": "2024-06-03",
        "createTime": "",
        "chapter": 649,
        "id": "94fef1de7e34453ab9b4d523415f4a49"
    },
    {
        "title": "斗破苍穹650天火尊者（12",
        "url": "https://xiongod.github.io/dpcq2/0650.m4a",
        "duration": "",
        "published": "2024-06-03",
        "createTime": "",
        "chapter": 650,
        "id": "518ffd7ff74c442883fc21f7c2eee9ba"
    },
    {
        "title": "斗破苍穹651五轮离火法（12",
        "url": "https://xiongod.github.io/dpcq2/0651.m4a",
        "duration": "",
        "published": "2024-06-03",
        "createTime": "",
        "chapter": 651,
        "id": "4819f98132f9481d85873014eb318765"
    },
    {
        "title": "斗破苍穹652陀舍古帝玉的动静（12",
        "url": "https://xiongod.github.io/dpcq2/0652.m4a",
        "duration": "",
        "published": "2024-06-03",
        "createTime": "",
        "chapter": 652,
        "id": "078846a13d2d4cfdb052359fe40b10f4"
    },
    {
        "title": "斗破苍穹653再次晋级（12",
        "url": "https://xiongod.github.io/dpcq2/0653.m4a",
        "duration": "",
        "published": "2024-06-03",
        "createTime": "",
        "chapter": 653,
        "id": "7314dfa8a52f48fabdc2d2aa6ab2f160"
    },
    {
        "title": "斗破苍穹654情报（12",
        "url": "https://xiongod.github.io/dpcq2/0654.m4a",
        "duration": "",
        "published": "2024-06-03",
        "createTime": "",
        "chapter": 654,
        "id": "2d733d2db0264742a6608f3155318183"
    },
    {
        "title": "斗破苍穹655召集人马（12",
        "url": "https://xiongod.github.io/dpcq2/0655.m4a",
        "duration": "",
        "published": "2024-06-03",
        "createTime": "",
        "chapter": 655,
        "id": "f82174acbcd0429cb41a6cb93decd6f3"
    },
    {
        "title": "斗破苍穹656联盟（12",
        "url": "https://xiongod.github.io/dpcq2/0656.m4a",
        "duration": "",
        "published": "2024-06-03",
        "createTime": "",
        "chapter": 656,
        "id": "534d85abb52d4bc5bfc21345436e5825"
    },
    {
        "title": "斗破苍穹657谈判（12",
        "url": "https://xiongod.github.io/dpcq2/0657.m4a",
        "duration": "",
        "published": "2024-06-03",
        "createTime": "",
        "chapter": 657,
        "id": "7ac24fc044dc48668934a2dbb4ddbeca"
    },
    {
        "title": "斗破苍穹658轩护法（12",
        "url": "https://xiongod.github.io/dpcq2/0658.m4a",
        "duration": "",
        "published": "2024-06-03",
        "createTime": "",
        "chapter": 658,
        "id": "528aff71ea754bdda087c80a9486c345"
    },
    {
        "title": "斗破苍穹659凶魂凝聚（12",
        "url": "https://xiongod.github.io/dpcq2/0659.m4a",
        "duration": "",
        "published": "2024-06-03",
        "createTime": "",
        "chapter": 659,
        "id": "257978d9f96a4e61ad04246a8cf00af9"
    },
    {
        "title": "斗破苍穹660收凶魂（12",
        "url": "https://xiongod.github.io/dpcq2/0660.m4a",
        "duration": "",
        "published": "2024-06-03",
        "createTime": "",
        "chapter": 660,
        "id": "189eb1f2915a4371bc9ee504ea217bfc"
    },
    {
        "title": "斗破苍穹661击杀轩护法（12",
        "url": "https://xiongod.github.io/dpcq2/0661.m4a",
        "duration": "",
        "published": "2024-06-03",
        "createTime": "",
        "chapter": 661,
        "id": "37f1b6e88a6f4112ab103688f84aa3b9"
    },
    {
        "title": "斗破苍穹662火莲，杀！（10",
        "url": "https://xiongod.github.io/dpcq2/0662.m4a",
        "duration": "",
        "published": "2024-06-03",
        "createTime": "",
        "chapter": 662,
        "id": "99f98e95ba3b4cb6b2c0748cc3504d9b"
    },
    {
        "title": "斗破苍穹663最后胜者（12",
        "url": "https://xiongod.github.io/dpcq2/0663.m4a",
        "duration": "",
        "published": "2024-06-03",
        "createTime": "",
        "chapter": 663,
        "id": "6298d2610a0c4f28ad4e94b543002411"
    },
    {
        "title": "斗破苍穹664寻宝（12",
        "url": "https://xiongod.github.io/dpcq2/0664.m4a",
        "duration": "",
        "published": "2024-06-03",
        "createTime": "",
        "chapter": 664,
        "id": "11298904ff6346c4b08abc6e16eed798"
    },
    {
        "title": "斗破苍穹665石洞库房（12",
        "url": "https://xiongod.github.io/dpcq2/0665.m4a",
        "duration": "",
        "published": "2024-06-03",
        "createTime": "",
        "chapter": 665,
        "id": "7cd774a1a65a4ed3bf517d858b70cd9b"
    },
    {
        "title": "斗破苍穹666天妖傀，养魂涎（12",
        "url": "https://xiongod.github.io/dpcq2/0666.m4a",
        "duration": "",
        "published": "2024-06-03",
        "createTime": "",
        "chapter": 666,
        "id": "d223cfd874b34e30a6956dc43fd99c0b"
    },
    {
        "title": "斗破苍穹667封印（12",
        "url": "https://xiongod.github.io/dpcq2/0667.m4a",
        "duration": "",
        "published": "2024-06-03",
        "createTime": "",
        "chapter": 667,
        "id": "3ede2bbac92a4823a9cbbfa0e0a706ce"
    },
    {
        "title": "斗破苍穹668炼化凶魂（12",
        "url": "https://xiongod.github.io/dpcq2/0668.m4a",
        "duration": "",
        "published": "2024-06-03",
        "createTime": "",
        "chapter": 668,
        "id": "8ba416e8857549bf939d9d827dcff655"
    },
    {
        "title": "斗破苍穹669炼制天妖傀（12",
        "url": "https://xiongod.github.io/dpcq2/0669.m4a",
        "duration": "",
        "published": "2024-06-03",
        "createTime": "",
        "chapter": 669,
        "id": "77015f0a15d64fd4af22f23f9e7f9ac6"
    },
    {
        "title": "斗破苍穹670炼制成功！（12",
        "url": "https://xiongod.github.io/dpcq2/0670.m4a",
        "duration": "",
        "published": "2024-06-03",
        "createTime": "",
        "chapter": 670,
        "id": "0381c75002d744a98fb882741ecd856c"
    },
    {
        "title": "斗破苍穹671大动静（12",
        "url": "https://xiongod.github.io/dpcq2/0671.m4a",
        "duration": "",
        "published": "2024-06-03",
        "createTime": "",
        "chapter": 671,
        "id": "d63c86fa269a448c866edd2a881ddce5"
    },
    {
        "title": "斗破苍穹672炼制天魂融血丹（12",
        "url": "https://xiongod.github.io/dpcq2/0672.m4a",
        "duration": "",
        "published": "2024-06-03",
        "createTime": "",
        "chapter": 672,
        "id": "2882055f224545deb0e819a0a2bb7795"
    },
    {
        "title": "斗破苍穹673血脉中的威压（12",
        "url": "https://xiongod.github.io/dpcq2/0673.m4a",
        "duration": "",
        "published": "2024-06-03",
        "createTime": "",
        "chapter": 673,
        "id": "fbb80fe213434a38932d0556216fa734"
    },
    {
        "title": "斗破苍穹674丹雷（12",
        "url": "https://xiongod.github.io/dpcq2/0674.m4a",
        "duration": "",
        "published": "2024-06-03",
        "createTime": "",
        "chapter": 674,
        "id": "48dd685b349444ec92f40f3057884d81"
    },
    {
        "title": "斗破苍穹675 再度突破！（12",
        "url": "https://xiongod.github.io/dpcq2/0675.m4a",
        "duration": "",
        "published": "2024-06-03",
        "createTime": "",
        "chapter": 675,
        "id": "c836eff265d64d3d91497e13d2e3ed05"
    },
    {
        "title": "斗破苍穹676离开（01",
        "url": "https://xiongod.github.io/dpcq2/0676.m4a",
        "duration": "",
        "published": "2024-06-03",
        "createTime": "",
        "chapter": 676,
        "id": "3d2bcb8da4dc472da2197cf485ce9080"
    },
    {
        "title": "斗破苍穹677一殿一塔，二宗三谷，四方阁（01",
        "url": "https://xiongod.github.io/dpcq2/0677.m4a",
        "duration": "",
        "published": "2024-06-03",
        "createTime": "",
        "chapter": 677,
        "id": "26bcf4bdbd2d493a9468b79132352fd7"
    },
    {
        "title": "斗破苍穹678空间虫洞，罗家（01",
        "url": "https://xiongod.github.io/dpcq2/0678.m4a",
        "duration": "",
        "published": "2024-06-03",
        "createTime": "",
        "chapter": 678,
        "id": "ca8127593c624483bb4f087bb0fc5c20"
    },
    {
        "title": "斗破苍穹679六阶天毒蝎龙兽（01",
        "url": "https://xiongod.github.io/dpcq2/0679.m4a",
        "duration": "",
        "published": "2024-06-03",
        "createTime": "",
        "chapter": 679,
        "id": "e783cf1d6a8846968a2f75500a5c71d4"
    },
    {
        "title": "斗破苍穹680修复，空间船（01",
        "url": "https://xiongod.github.io/dpcq2/0680.m4a",
        "duration": "",
        "published": "2024-06-03",
        "createTime": "",
        "chapter": 680,
        "id": "c18feafd5fb94b85804f8517cd61a1a7"
    },
    {
        "title": "斗破苍穹681空间风暴（01",
        "url": "https://xiongod.github.io/dpcq2/0681.m4a",
        "duration": "",
        "published": "2024-06-03",
        "createTime": "",
        "chapter": 681,
        "id": "520d2b6c43dd4c0890ca012c9e64f5a9"
    },
    {
        "title": "斗破苍穹682韩冲，被救（01",
        "url": "https://xiongod.github.io/dpcq2/0682.m4a",
        "duration": "",
        "published": "2024-06-03",
        "createTime": "",
        "chapter": 682,
        "id": "d9128e38648946c28804cdf16b58ff50"
    },
    {
        "title": "斗破苍穹683妖蛇夏莽（01",
        "url": "https://xiongod.github.io/dpcq2/0683.m4a",
        "duration": "",
        "published": "2024-06-03",
        "createTime": "",
        "chapter": 683,
        "id": "dda143f97afd429480c1ce99558f3161"
    },
    {
        "title": "斗破苍穹684万蛇峡（01",
        "url": "https://xiongod.github.io/dpcq2/0684.m4a",
        "duration": "",
        "published": "2024-06-03",
        "createTime": "",
        "chapter": 684,
        "id": "c696bfc6fffd4e07acc0e423c78c8e61"
    },
    {
        "title": "斗破苍穹685神秘强者（01",
        "url": "https://xiongod.github.io/dpcq2/0685.m4a",
        "duration": "",
        "published": "2024-06-03",
        "createTime": "",
        "chapter": 685,
        "id": "749a143c0fd84a04a162b2552e61397a"
    },
    {
        "title": "斗破苍穹686洪家（01",
        "url": "https://xiongod.github.io/dpcq2/0686.m4a",
        "duration": "",
        "published": "2024-06-03",
        "createTime": "",
        "chapter": 686,
        "id": "2232d275f0bc4cb6b7d64181cba6f61a"
    },
    {
        "title": "斗破苍穹687出手（01",
        "url": "https://xiongod.github.io/dpcq2/0687.m4a",
        "duration": "",
        "published": "2024-06-03",
        "createTime": "",
        "chapter": 687,
        "id": "1a1f9ffd345b44059bb47b694000b71b"
    },
    {
        "title": "斗破苍穹688天北城（01",
        "url": "https://xiongod.github.io/dpcq2/0688.m4a",
        "duration": "",
        "published": "2024-06-03",
        "createTime": "",
        "chapter": 688,
        "id": "b7c10dee9ffd4aa6b9cbae356b5f2502"
    },
    {
        "title": "斗破苍穹689 熟人（01",
        "url": "https://xiongod.github.io/dpcq2/0689.m4a",
        "duration": "",
        "published": "2024-06-03",
        "createTime": "",
        "chapter": 689,
        "id": "7c109177deba48aba8a025770ebd01c8"
    },
    {
        "title": "斗破苍穹690九转风游步（01",
        "url": "https://xiongod.github.io/dpcq2/0690.m4a",
        "duration": "",
        "published": "2024-06-03",
        "createTime": "",
        "chapter": 690,
        "id": "02ef7067eec842618bb3aaaafa106639"
    },
    {
        "title": "斗破苍穹691诸乾（01",
        "url": "https://xiongod.github.io/dpcq2/0691.m4a",
        "duration": "",
        "published": "2024-06-03",
        "createTime": "",
        "chapter": 691,
        "id": "24ee393554e64cb8940bf19c05d101fb"
    },
    {
        "title": "斗破苍穹692天石台比斗（01",
        "url": "https://xiongod.github.io/dpcq2/0692.m4a",
        "duration": "",
        "published": "2024-06-03",
        "createTime": "",
        "chapter": 692,
        "id": "57cadce72eca4e71aad109c60274c372"
    },
    {
        "title": "斗破苍穹693交手（01",
        "url": "https://xiongod.github.io/dpcq2/0693.m4a",
        "duration": "",
        "published": "2024-06-03",
        "createTime": "",
        "chapter": 693,
        "id": "72b3afbf69d94595b43d6488f8db3df3"
    },
    {
        "title": "斗破苍穹694灭雷锤！（01",
        "url": "https://xiongod.github.io/dpcq2/0694.m4a",
        "duration": "",
        "published": "2024-06-03",
        "createTime": "",
        "chapter": 694,
        "id": "80ed3f4394914d52bb7eee5d781bb05e"
    },
    {
        "title": "斗破苍穹695变故（01",
        "url": "https://xiongod.github.io/dpcq2/0695.m4a",
        "duration": "",
        "published": "2024-06-03",
        "createTime": "",
        "chapter": 695,
        "id": "537a4eba5bf441ceb41ce440d545b202"
    },
    {
        "title": "斗破苍穹696不够资格（01",
        "url": "https://xiongod.github.io/dpcq2/0696.m4a",
        "duration": "",
        "published": "2024-06-03",
        "createTime": "",
        "chapter": 696,
        "id": "f7cd505804ba4b71ad8af19fd8079504"
    },
    {
        "title": "斗破苍穹697洪家围剿（01",
        "url": "https://xiongod.github.io/dpcq2/0697.m4a",
        "duration": "",
        "published": "2024-06-03",
        "createTime": "",
        "chapter": 697,
        "id": "cffbb928e4ae412f9ffecca62907fe49"
    },
    {
        "title": "斗破苍穹698杀伐果断（01",
        "url": "https://xiongod.github.io/dpcq2/0698.m4a",
        "duration": "",
        "published": "2024-06-03",
        "createTime": "",
        "chapter": 698,
        "id": "c7822dd3e299442a86a5eb37f8fcaaec"
    },
    {
        "title": "斗破苍穹699三千雷幻身（01",
        "url": "https://xiongod.github.io/dpcq2/0699.m4a",
        "duration": "",
        "published": "2024-06-03",
        "createTime": "",
        "chapter": 699,
        "id": "910de950dda141b8ace474cbfa9d2f17"
    }
]